Workbook

Sheet RECETTES
B2: TABLEAU DETAILLE DES RECETTES
E4: COLLECTIVITE : …..........
B6: RECETTES DE FONCTIONNEMENT
B7: COMPTE | E7: INTITULES | F7: BUDGET PRIMITIF | G7: BUDGET ADDITIONNEL | H7: MODIFICATIONS +/- | I7: PREVISIONS DEFINITIVES (1) | J7: OR ADMIS (2) | K7: RECOUVREMENT | L7: RESTE A RECOUVRER | M7: TAUX D'EXECUTION (2)/(1)
B8: 70 | E8: IMPOTS SUR LES REVENUS, BENEFICES ET GAINS | F8: =SUM(F9) -> 0 | G8: =SUM(G9) -> 0 | H8: =SUM(H9) -> 0 | I8: =SUM(I9) -> 0 | J8: =SUM(J9) -> 0 | K8: =SUM(K9) -> 0 | L8: =SUM(L9) -> 0 | M8: =J8/I8 -> #DIV/0!
C9: 708 | E9: Autres impôts sur les revenus | F9: =SUM(F10) -> 0 | G9: =SUM(G10) -> 0 | H9: =SUM(H10) -> 0 | I9: =SUM(I10) -> 0 | J9: =SUM(J10) -> 0 | K9: =SUM(K10) -> 0 | L9: =J9-K9 -> 0
D10: 7080 | E10: Autres impôts sur les revenus - Impôt synthétique | L10: =J10-K10 -> 0 | M10: =J10/I10 -> #DIV/0!
B11: 71 | E11: IMPOTS SUR LE PATRIMOINE | F11: =SUM(F12,F14,F17) -> 0 | G11: =SUM(G12,G14,G17) -> 0 | H11: =SUM(H12,H14,H17) -> 0 | I11: =SUM(I12,I14,I17) -> 0 | J11: =SUM(J12,J14,J17) -> 0 | K11: =SUM(K12,K14,K17) -> 0 | L11: =SUM(L12,L14,L17) -> 0 | M11: =J11/I11 -> #DIV/0!
C12: 714 | E12: Impôts fonciers sur les terrains - IFT | F12: =SUM(F13) -> 0 | G12: =SUM(G13) -> 0 | H12: =SUM(H13) -> 0 | I12: =SUM(I13) -> 0 | J12: =SUM(J13) -> 0 | K12: =SUM(K13) -> 0 | L12: =J12-K12 -> 0
D13: 7140 | E13: Impôts fonciers sur les terrains - IFT | L13: =J13-K13 -> 0 | M13: =J13/I13 -> #DIV/0!
C14: 715 | E14: Impôt foncier sur les propriétés bâties – IFPB | F14: =SUM(F15:F16) -> 0 | G14: =SUM(G15:G16) -> 0 | H14: =SUM(H15:H16) -> 0 | I14: =SUM(I15:I16) -> 0 | J14: =SUM(J15:J16) -> 0 | K14: =SUM(K15:K16) -> 0 | L14: =J14-K14 -> 0
D15: 7151 | E15: Impôt foncier sur les propriétés bâties – IFPB | L15: =J15-K15 -> 0 | M15: =J15/I15 -> #DIV/0!
D16: 7158 | E16: Autres impôts locaux sur les propriétés baties | L16: =J16-K16 -> 0 | M16: =J16/I16 -> #DIV/0!
C17: 718 | E17: Taxe annuelle sur autres patrimoines | F17: =SUM(F18:F20) -> 0 | G17: =SUM(G18:G20) -> 0 | H17: =SUM(H18:H20) -> 0 | I17: =SUM(I18:I20) -> 0 | J17: =SUM(J18:J20) -> 0 | K17: =SUM(K18:K20) -> 0 | L17: =J17-K17 -> 0
D18: 7181 | E18: Taxes sur les appareils automatiques ou électroniques | L18: =J18-K18 -> 0 | M18: =J18/I18 -> #DIV/0!
D19: 7182 | E19: Taxes sur les appareils mecaniques | L19: =J19-K19 -> 0 | M19: =J19/I19 -> #DIV/0!
D20: 7188 | E20: Autres taxes et impots annuels | L20: =J20-K20 -> 0 | M20: =J20/I20 -> #DIV/0!
B21: 72 | E21: IMPOTS SUR LES BIENS ET SERVICES | F21: =SUM(F22,F28,F33,F39) -> 0 | G21: =SUM(G22,G28,G33,G39) -> 0 | H21: =SUM(H22,H28,H33,H39) -> 0 | I21: =SUM(I22,I28,I33,I39) -> 0 | J21: =SUM(J22,J28,J33,J39) -> 0 | K21: =SUM(K22,K28,K33,K39) -> 0 | L21: =SUM(L22,L28,L33,L39) -> 0 | M21: =J21/I21 -> #DIV/0!
C22: 725 | E22: Taxes particulières sur les biens | F22: =SUM(F23:F27) -> 0 | G22: =SUM(G23:G27) -> 0 | H22: =SUM(H23:H27) -> 0 | I22: =SUM(I23:I27) -> 0 | J22: =SUM(J23:J27) -> 0 | K22: =SUM(K23:K27) -> 0 | L22: =J22-K22 -> 0
D23: 7251 | E23: Taxes sur l'électricité | L23: =J23-K23 -> 0 | M23: =J23/I23 -> #DIV/0!
D24: 7252 | E24: Taxes sur l'eau | L24: =J24-K24 -> 0 | M24: =J24/I24 -> #DIV/0!
D25: 7253 | E25: Surtaxe sur l'eau et l'électricité | L25: =J25-K25 -> 0 | M25: =J25/I25 -> #DIV/0!
D26: 7254 | E26: Taxes sur les eaux minérales | L26: =J26-K26 -> 0 | M26: =J26/I26 -> #DIV/0!
D27: 7258 | E27: Autres taxes particulières sur les biens | L27: =J27-K27 -> 0 | M27: =J27/I27 -> #DIV/0!
C28: 726 | E28: Taxes particulières sur les services | F28: =SUM(F29:F32) -> 0 | G28: =SUM(G29:G32) -> 0 | H28: =SUM(H29:H32) -> 0 | I28: =SUM(I29:I32) -> 0 | J28: =SUM(J29:J32) -> 0 | K28: =SUM(K29:K32) -> 0 | L28: =J28-K28 -> 0
D29: 7261 | E29: taxes sur la publicité | L29: =J29-K29 -> 0 | M29: =J29/I29 -> #DIV/0!
D30: 7262 | E30: Taxe d’abattage | L30: =J30-K30 -> 0 | M30: =J30/I30 -> #DIV/0!
D31: 7263 | E31: Taxe de visite et de poinçonnage des viandes | L31: =J31-K31 -> 0 | M31: =J31/I31 -> #DIV/0!
D32: 7268 | E32: Autres taxes locales sur les services | L32: =J32-K32 -> 0 | M32: =J32/I32 -> #DIV/0!
C33: 727 | E33: Taxes particulières sur les activités | F33: =SUM(F34:F38) -> 0 | G33: =SUM(G34:G38) -> 0 | H33: =SUM(H34:H38) -> 0 | I33: =SUM(I34:I38) -> 0 | J33: =SUM(J34:J38) -> 0 | K33: =SUM(K34:K38) -> 0 | L33: =J33-K33 -> 0
D34: 7273 | E34: Impôt de licence | L34: =J34-K34 -> 0 | M34: =J34/I34 -> #DIV/0!
D35: 7274 | E35: Prélèvement sur les produits de jeux - PPJ | L35: =J35-K35 -> 0 | M35: =J35/I35 -> #DIV/0!
D36: 7276 | E36: Taxes sur les fêtes, spectacles et manifestations… | L36: =J36-K36 -> 0 | M36: =J36/I36 -> #DIV/0!
D37: 7277 | E37: Taxes sur les établissements exerçant des activités à but lucratif | L37: =J37-K37 -> 0 | M37: =J37/I37 -> #DIV/0!
D38: 7278 | E38: Autres taxes locales sur les activités | L38: =J38-K38 -> 0 | M38: =J38/I38 -> #DIV/0!
C39: 728 | E39: Autres impôts sur les biens et services | F39: =SUM(F40) -> 0 | G39: =SUM(G40) -> 0 | H39: =SUM(H40) -> 0 | I39: =SUM(I40) -> 0 | J39: =SUM(J40) -> 0 | K39: =SUM(K40) -> 0 | L39: =J39-K39 -> 0
D40: 7280 | E40: Autres impôts sur les biens et services | L40: =J40-K40 -> 0 | M40: =J40/I40 -> #DIV/0!
B41: 74 | E41: AUTRES RECETTES FISCALES | F41: =SUM(F42,F46) -> 0 | G41: =SUM(G42,G46) -> 0 | H41: =SUM(H42,H46) -> 0 | I41: =SUM(I42,I46) -> 0 | J41: =SUM(J42,J46) -> 0 | K41: =SUM(K42,K46) -> 0 | L41: =SUM(L42,L46) -> 0 | M41: =J41/I41 -> #DIV/0!
C42: 743 | E42: Amendes fiscales et pénalités | F42: =SUM(F43:F45) -> 0 | G42: =SUM(G43:G45) -> 0 | H42: =SUM(H43:H45) -> 0 | I42: =SUM(I43:I45) -> 0 | J42: =SUM(J43:J45) -> 0 | K42: =SUM(K43:K45) -> 0 | L42: =J42-K42 -> 0
D43: 7431 | E43: Amendes fiscales | L43: =J43-K43 -> 0 | M43: =J43/I43 -> #DIV/0!
D44: 7432 | E44: Pénalité | L44: =J44-K44 -> 0 | M44: =J44/I44 -> #DIV/0!
D45: 7433 | E45: Intérêt moratoire | L45: =J45-K45 -> 0 | M45: =J45/I45 -> #DIV/0!
C46: 748 | E46: Taxes diverses | F46: =SUM(F47) -> 0 | G46: =SUM(G47) -> 0 | H46: =SUM(H47) -> 0 | I46: =SUM(I47) -> 0 | J46: =SUM(J47) -> 0 | K46: =SUM(K47) -> 0 | L46: =J46-K46 -> 0
D47: 7482 | E47: Droits et taxes diverses : Activités agricoles | L47: =J47-K47 -> 0 | M47: =J47/I47 -> #DIV/0!
B48: 75 | E48: CONTRIBUTIONS RECUES DES TIERS | F48: =SUM(F49,F54,F59) -> 0 | G48: =SUM(G49,G54,G59) -> 0 | H48: =SUM(H49,H54,H59) -> 0 | I48: =SUM(I49,I54,I59) -> 0 | J48: =SUM(J49,J54,J59) -> 0 | K48: =SUM(K49,K54,K59) -> 0 | L48: =SUM(L49,L54,L59) -> 0 | M48: =J48/I48 -> #DIV/0!
C49: 751 | E49: Subvention d'exploitation - Etat | F49: =SUM(F50:F53) -> 0 | G49: =SUM(G50:G53) -> 0 | H49: =SUM(H50:H53) -> 0 | I49: =SUM(I50:I53) -> 0 | J49: =SUM(J50:J53) -> 0 | K49: =SUM(K50:K53) -> 0 | L49: =J49-K49 -> 0
D50: 7511 | E50: Dotation globale -EPP | L50: =J50-K50 -> 0 | M50: =J50/I50 -> #DIV/0!
D51: 7512 | E51: Dotation globale -CSB | L51: =J51-K51 -> 0 | M51: =J51/I51 -> #DIV/0!
D52: 7513 | E52: Dotation globale -Etat civil | L52: =J52-K52 -> 0 | M52: =J52/I52 -> #DIV/0!
D53: 7518 | E53: Dotation globale -Autres | L53: =J53-K53 -> 0 | M53: =J53/I53 -> #DIV/0!
C54: 752 | E54: Subventions d'exploitation reçcues des Collectivités Publiques | F54: =SUM(F55:F58) -> 0 | G54: =SUM(G55:G58) -> 0 | H54: =SUM(H55:H58) -> 0 | I54: =SUM(I55:I58) -> 0 | J54: =SUM(J55:J58) -> 0 | K54: =SUM(K55:K58) -> 0 | L54: =J54-K54 -> 0
D55: 7522 | E55: Collectivités Territoriales Décentralisées | L55: =J55-K55 -> 0 | M55: =J55/I55 -> #DIV/0!
D56: 7523 | E56: Etablissements Publics à caractère Industriel et Commercial (EPIC) | L56: =J56-K56 -> 0 | M56: =J56/I56 -> #DIV/0!
D57: 7524 | E57: Etablissements Publics à caractère Administratifs (EPA) | L57: =J57-K57 -> 0 | M57: =J57/I57 -> #DIV/0!
D58: 7528 | E58: Autres Collectivités Publiques | L58: =J58-K58 -> 0 | M58: =J58/I58 -> #DIV/0!
C59: 755 | E59: Organismes privés locaux | F59: =SUM(F60) -> 0 | G59: =SUM(G60) -> 0 | H59: =SUM(H60) -> 0 | I59: =SUM(I60) -> 0 | J59: =SUM(J60) -> 0 | K59: =SUM(K60) -> 0 | L59: =J59-K59 -> 0
D60: 7550 | E60: organisme privée locaux | L60: =J60-K60 -> 0 | M60: =J60/I60 -> #DIV/0!
B61: 76 | E61: PRODUITS FINANCIERS | F61: =SUM(F62,F64,F67,F69,F72) -> 0 | G61: =SUM(G62,G64,G67,G69,G72) -> 0 | H61: =SUM(H62,H64,H67,H69,H72) -> 0 | I61: =SUM(I62,I64,I67,I69,I72) -> 0 | J61: =SUM(J62,J64,J67,J69,J72) -> 0 | K61: =SUM(K62,K64,K67,K69,K72) -> 0 | L61: =SUM(L62,L64,L67,L69,L72) -> 0 | M61: =J61/I61 -> #DIV/0!
C62: 761 | E62: Produits des prises de participation | F62: =SUM(F63) -> 0 | G62: =SUM(G63) -> 0 | H62: =SUM(H63) -> 0 | I62: =SUM(I63) -> 0 | J62: =SUM(J63) -> 0 | K62: =SUM(K63) -> 0 | L62: =J62-K62 -> 0
D63: 7610 | E63: Produits des prises de participation | L63: =J63-K63 -> 0 | M63: =J63/I63 -> #DIV/0!
C64: 762 | E64: Produits des autres immobilisations financières | F64: =SUM(F65:F66) -> 0 | G64: =SUM(G65:G66) -> 0 | H64: =SUM(H65:H66) -> 0 | I64: =SUM(I65:I66) -> 0 | J64: =SUM(J65:J66) -> 0 | K64: =SUM(K65:K66) -> 0 | L64: =J64-K64 -> 0
D65: 7621 | E65: Revenus des obligations et bons à plus d'un an | L65: =J65-K65 -> 0 | M65: =J65/I65 -> #DIV/0!
D66: 7622 | E66: Revenus des prêts à long et moyen terme | L66: =J66-K66 -> 0 | M66: =J66/I66 -> #DIV/0!
C67: 763 | E67: Revenus des autres créances | F67: =SUM(F68) -> 0 | G67: =SUM(G68) -> 0 | H67: =SUM(H68) -> 0 | I67: =SUM(I68) -> 0 | J67: =SUM(J68) -> 0 | K67: =SUM(K68) -> 0 | L67: =J67-K67 -> 0
D68: 7630 | E68: Revenus des autres créances | L68: =J68-K68 -> 0 | M68: =J68/I68 -> #DIV/0!
C69: 764 | E69: Revenus des titres de placement et des prêts à court terme | F69: =SUM(F70:F71) -> 0 | G69: =SUM(G70:G71) -> 0 | H69: =SUM(H70:H71) -> 0 | I69: =SUM(I70:I71) -> 0 | J69: =SUM(J70:J71) -> 0 | K69: =SUM(K70:K71) -> 0 | L69: =J69-K69 -> 0
D70: 7641 | E70: Revenus des obligations et bons à court terme | L70: =J70-K70 -> 0 | M70: =J70/I70 -> #DIV/0!
D71: 7642 | E71: Revenus des prêts à court terme | L71: =J71-K71 -> 0 | M71: =J71/I71 -> #DIV/0!
C72: 768 | E72: Autres produits financiers | F72: =SUM(F73) -> 0 | G72: =SUM(G73) -> 0 | H72: =SUM(H73) -> 0 | I72: =SUM(I73) -> 0 | J72: =SUM(J73) -> 0 | K72: =SUM(K73) -> 0 | L72: =J72-K72 -> 0
D73: 7680 | E73: Autres produits financiers | L73: =J73-K73 -> 0 | M73: =J73/I73 -> #DIV/0!
B74: 77 | E74: RECETTES NON FISCALES | F74: =SUM(F75,F84,F93) -> 0 | G74: =SUM(G75,G84,G93) -> 0 | H74: =SUM(H75,H84,H93) -> 0 | I74: =SUM(I75,I84,I93) -> 0 | J74: =SUM(J75,J84,J93) -> 0 | K74: =SUM(K75,K84,K93) -> 0 | L74: =SUM(L75,L84,L93) -> 0 | M74: =J74/I74 -> #DIV/0!
C75: 771 | E75: Redevances | F75: =SUM(F76:F83) -> 0 | G75: =SUM(G76:G83) -> 0 | H75: =SUM(H76:H83) -> 0 | I75: =SUM(I76:I83) -> 0 | J75: =SUM(J76:J83) -> 0 | K75: =SUM(K76:K83) -> 0 | L75: =J75-K75 -> 0
D76: 7711 | E76: Redevances de collecte et de traitement des ordures ménagères - ROM | L76: =J76-K76 -> 0 | M76: =J76/I76 -> #DIV/0!
D77: 7712 | E77: Redevances de rejet des eaux usées - RREU | L77: =J77-K77 -> 0 | M77: =J77/I77 -> #DIV/0!
D78: 7713 | E78: Redevance et frais d'administration minière | L78: =J78-K78 -> 0 | M78: =J78/I78 -> #DIV/0!
D79: 7714 | E79: Redevances sur autorisations administratives | L79: =J79-K79 -> 0 | M79: =J79/I79 -> #DIV/0!
D80: 7715 | E80: Redevance fixe d'abonnement pour branchement | L80: =J80-K80 -> 0 | M80: =J80/I80 -> #DIV/0!
D81: 7716 | E81: Redevance versées par les fermiers et concessionnaires | L81: =J81-K81 -> 0 | M81: =J81/I81 -> #DIV/0!
D82: 7717 | E82: Produits des ristournes | L82: =J82-K82 -> 0 | M82: =J82/I82 -> #DIV/0!
D83: 7718 | E83: Autres redevances locales | L83: =J83-K83 -> 0 | M83: =J83/I83 -> #DIV/0!
C84: 772 | E84: Produits des activités des services | F84: =SUM(F85:F92) -> 0 | G84: =SUM(G85:G92) -> 0 | H84: =SUM(H85:H92) -> 0 | I84: =SUM(I85:I92) -> 0 | J84: =SUM(J85:J92) -> 0 | K84: =SUM(K85:K92) -> 0 | L84: =J84-K84 -> 0
D85: 7721 | E85: Prestation de service | L85: =J85-K85 -> 0 | M85: =J85/I85 -> #DIV/0!
D86: 7722 | E86: Produits finis | L86: =J86-K86 -> 0 | M86: =J86/I86 -> #DIV/0!
D87: 7723 | E87: Produits intermédiaires | L87: =J87-K87 -> 0 | M87: =J87/I87 -> #DIV/0!
D88: 7724 | E88: Produits résiduels | L88: =J88-K88 -> 0 | M88: =J88/I88 -> #DIV/0!
D89: 7725 | E89: Travaux | L89: =J89-K89 -> 0 | M89: =J89/I89 -> #DIV/0!
D90: 7726 | E90: Marchandises | L90: =J90-K90 -> 0 | M90: =J90/I90 -> #DIV/0!
D91: 7727 | E91: revenus des domaines | L91: =J91-K91 -> 0 | M91: =J91/I91 -> #DIV/0!
D92: 7728 | E92: Autres produits des activités des services | L92: =J92-K92 -> 0 | M92: =J92/I92 -> #DIV/0!
C93: 773 | E93: Produits des activités annexes et accessoires | F93: =SUM(F94:F99) -> 0 | G93: =SUM(G94:G99) -> 0 | H93: =SUM(H94:H99) -> 0 | I93: =SUM(I94:I99) -> 0 | J93: =SUM(J94:J99) -> 0 | K93: =SUM(K94:K99) -> 0 | L93: =J93-K93 -> 0
D94: 7731 | E94: Commissions et courtages | L94: =J94-K94 -> 0 | M94: =J94/I94 -> #DIV/0!
D95: 7732 | E95: Locations diverses | L95: =J95-K95 -> 0 | M95: =J95/I95 -> #DIV/0!
D96: 7733 | E96: Confiscations | L96: =J96-K96 -> 0 | M96: =J96/I96 -> #DIV/0!
D97: 7734 | E97: Droit de fourrières | L97: =J97-K97 -> 0 | M97: =J97/I97 -> #DIV/0!
D98: 7735 | E98: Droit de stationnement | L98: =J98-K98 -> 0 | M98: =J98/I98 -> #DIV/0!
D99: 7738 | E99: Autres | L99: =J99-K99 -> 0 | M99: =J99/I99 -> #DIV/0!
E100: TOTAL RECETTES REELLES DE FONCTIONNEMENT | F100: =F8+F11+F21+F41+F48+F61+F74 -> 0 | G100: =G8+G11+G21+G41+G48+G61+G74 -> 0 | H100: =H8+H11+H21+H41+H48+H61+H74 -> 0 | I100: =I8+I11+I21+I41+I48+I61+I74 -> 0 | J100: =J8+J11+J21+J41+J48+J61+J74 -> 0 | K100: =K8+K11+K21+K41+K48+K61+K74 -> 0 | L100: =L8+L11+L21+L41+L48+L61+L74 -> 0 | M100: =J100/I100 -> #DIV/0!
C101: 774 | E101: Production immobilisée | F101: =SUM(F102:F103) -> 0 | G101: =SUM(G102:G103) -> 0 | H101: =SUM(H102:H103) -> 0 | I101: =SUM(I102:I103) -> 0 | J101: =SUM(J102:J103) -> 0 | K101: =SUM(K102:K103) -> 0 | L101: =J101-K101 -> 0
D102: 7741 | E102: Immobilisation incorporelle | L102: =J102-K102 -> 0 | M102: =J102/I102 -> #DIV/0!
D103: 7742 | E103: Immobilisations corporelle | L103: =J103-K103 -> 0 | M103: =J103/I103 -> #DIV/0!
...

Sheet RECAPITULATIF RECETTES
B2: RECAPITULATIF DES RECETTES
E4: COLLECTIVITE : …..........
B6: RECETTES DE FONCTIONNEMENT
B7: COMPTE | E7: INTITULES | F7: PREVISIONS DEFINITIVES | G7: OR ADMIS | H7: RECOUVREMENT | I7: RESTE A RECOUVRER
B8: 70 | E8: IMPOTS SUR LES REVENUS, BENEFICES ET GAINS | F8: =RECETTES!I8 -> 0 | G8: =RECETTES!J8 -> 0 | H8: =RECETTES!K8 -> 0 | I8: =RECETTES!L8 -> 0
B9: 71 | E9: IMPOTS SUR LE PATRIMOINE | F9: =RECETTES!I11 -> 0 | G9: =RECETTES!J11 -> 0 | H9: =RECETTES!K11 -> 0 | I9: =RECETTES!L11 -> 0
B10: 72 | E10: IMPOTS SUR LES BIENS ET SERVICES | F10: =RECETTES!I21 -> 0 | G10: =RECETTES!J21 -> 0 | H10: =RECETTES!K21 -> 0 | I10: =RECETTES!L21 -> 0
B11: 74 | E11: AUTRES RECETTES FISCALES | F11: =RECETTES!I41 -> 0 | G11: =RECETTES!J41 -> 0 | H11: =RECETTES!K41 -> 0 | I11: =RECETTES!L41 -> 0
B12: 75 | E12: CONTRIBUTIONS RECUES DES TIERS | F12: =RECETTES!I48 -> 0 | G12: =RECETTES!J48 -> 0 | H12: =RECETTES!K48 -> 0 | I12: =RECETTES!L48 -> 0
B13: 76 | E13: PRODUITS FINANCIERS | F13: =RECETTES!I61 -> 0 | G13: =RECETTES!J61 -> 0 | H13: =RECETTES!K61 -> 0 | I13: =RECETTES!L61 -> 0
B14: 77 | E14: RECETTES NON FISCALES | F14: =RECETTES!I74 -> 0 | G14: =RECETTES!J74 -> 0 | H14: =RECETTES!K74 -> 0 | I14: =RECETTES!L74 -> 0
E15: TOTAL RECETTES REELLES DE FONCTIONNEMENT | F15: =F8+F9+F10+F11+F12+F13+F14 -> 0 | G15: =G8+G9+G10+G11+G12+G13+G14 -> 0 | H15: =H8+H9+H10+H11+H12+H13+H14 -> 0 | I15: =I8+I9+I10+I11+I12+I13+I14 -> 0
E16: TOTAL RECETTES D'ORDRE FONCTIONNEMENT | F16: =RECETTES!I104 -> 0 | G16: =RECETTES!J104 -> 0 | H16: =RECETTES!K104 -> 0 | I16: =RECETTES!L104 -> 0
E17: SOUS-TOTAL FONCTIONNEMENT | F17: =F15+F16 -> 0 | G17: =G15+G16 -> 0 | H17: =H15+H16 -> 0 | I17: =I15+I16 -> 0
B19: RECETTE D'INVESTISSEMENT
B20: COMPTE | E20: INTITULE | F20: PREVISIONS DEFINITIVES | G20: OR ADMIS | H20: RECOUVREMENT | I20: RESTE A RECOUVRER
B21: 10 | E21: FONDS, DOTATIONS ET RESERVES | F21: =RECETTES!I109 -> 0 | G21: =RECETTES!J109 -> 0 | H21: =RECETTES!K109 -> 0 | I21: =RECETTES!L109 -> 0
B22: 13 | E22: SUBVENTIONS D'EQUIPEMENT | F22: =RECETTES!I123 -> 0 | G22: =RECETTES!J123 -> 0 | H22: =RECETTES!K123 -> 0 | I22: =RECETTES!L123 -> 0
B23: 14 | E23: CESSIONS D'IMMOBILISATIONS | F23: =RECETTES!I133 -> 0 | G23: =RECETTES!J133 -> 0 | H23: =RECETTES!K133 -> 0 | I23: =RECETTES!L133 -> 0
B24: 16 | E24: EMPRUNTS ET DETTES ASSIMILEES | F24: =RECETTES!I152 -> 0 | G24: =RECETTES!J152 -> 0 | H24: =RECETTES!K152 -> 0 | I24: =RECETTES!L152 -> 0
E25: TOTAL RECETTES REELLES INVESTISSEMENT | F25: =F21+F22+F23+F24 -> 0 | G25: =G21+G22+G23+G24 -> 0 | H25: =H21+H22+H23+H24 -> 0 | I25: =I21+I22+I23+I24 -> 0
B26: 10 | E26: FONDS, DOTATIONS ET RESERVES | F26: =RECETTES!I167 -> 0 | G26: =RECETTES!J167 -> 0 | H26: =RECETTES!K167 -> 0 | I26: =RECETTES!L167 -> 0
E27: RECETTE D'ORDRE INVESTISSEMENT | F27: =F26 -> 0 | G27: =G26 -> 0 | H27: =H26 -> 0 | I27: =I26 -> 0
E28: SOUS-TOTAL INVESTISSEMENT | F28: =F25+F27 -> 0 | G28: =G25+G27 -> 0 | H28: =H25+H27 -> 0 | I28: =I25+I27 -> 0

Sheet DEPENSES PROGRAMME I
B2: TABLEAU DETAILLE DES DEPENSES
E4: COLLECTIVITE : …..........
E6: PROGRAMME I :
B8: DEPENSES DE FONCTIONNEMENT
B9: COMPTE | E9: INTITULES | F9: BUDGET PRIMITIF | G9: BUDGET ADDITIONNEL | H9: MODIFICATIONS +/- | I9: PREVISIONS DEFINITIVES (1) | J9: ENGAGEMENT | K9: MANDAT ADMIS (2) | L9: PAIEMENT | M9: RESTE A PAYER | N9: TAUX D'EXECUTION (2)/(1)
B10: 60 | E10: CHARGES DE PERSONNEL | F10: =SUM(F11,F14,F17,F20,F23) -> 0 | G10: =SUM(G11,G14,G17,G20,G23) -> 0 | H10: =SUM(H11,H14,H17,H20,H23) -> 0 | I10: =SUM(I11,I14,I17,I20,I23) -> 0 | J10: =SUM(J11,J14,J17,J20,J23) -> 0 | K10: =SUM(K11,K14,K17,K20,K23) -> 0 | L10: =SUM(L11,L14,L17,L20,L23) -> 0 | M10: =SUM(M11,M14,M17,M20,M23) -> 0 | N10: =K10/I10 -> #DIV/0!
C11: 601 | E11: Salaires et accessoires | F11: =SUM(F12:F13) -> 0 | G11: =SUM(G12:G13) -> 0 | H11: =SUM(H12:H13) -> 0 | I11: =SUM(I12:I13) -> 0 | J11: =SUM(J12:J13) -> 0 | K11: =SUM(K12:K13) -> 0 | L11: =SUM(L12:L13) -> 0 | M11: =K11-L11 -> 0
D12: 6011 | E12: Personnel permanent | M12: =K12-L12 -> 0 | N12: =K12/I12 -> #DIV/0!
D13: 6012 | E13: Personnel non permanent | M13: =K13-L13 -> 0 | N13: =K13/I13 -> #DIV/0!
C14: 602 | E14: Indemnités liées à la solde | F14: =SUM(F15:F16) -> 0 | G14: =SUM(G15:G16) -> 0 | H14: =SUM(H15:H16) -> 0 | I14: =SUM(I15:I16) -> 0 | J14: =SUM(J15:J16) -> 0 | K14: =SUM(K15:K16) -> 0 | L14: =SUM(L15:L16) -> 0 | M14: =K14-L14 -> 0
D15: 6021 | E15: Personnel permanent | M15: =K15-L15 -> 0 | N15: =K15/I15 -> #DIV/0!
D16: 6022 | E16: Personnel non permanent | M16: =K16-L16 -> 0 | N16: =K16/I16 -> #DIV/0!
C17: 603 | E17: Indemnités et avantages liés à la fonction | F17: =SUM(F18:F19) -> 0 | G17: =SUM(G18:G19) -> 0 | H17: =SUM(H18:H19) -> 0 | I17: =SUM(I18:I19) -> 0 | J17: =SUM(J18:J19) -> 0 | K17: =SUM(K18:K19) -> 0 | L17: =SUM(L18:L19) -> 0 | M17: =K17-L17 -> 0
D18: 6031 | E18: Personnel permanent | M18: =K18-L18 -> 0 | N18: =K18/I18 -> #DIV/0!
D19: 6032 | E19: Personnel non permanent | M19: =K19-L19 -> 0 | N19: =K19/I19 -> #DIV/0!
C20: 604 | E20: Supplément familial de traitement | F20: =SUM(F21:F22) -> 0 | G20: =SUM(G21:G22) -> 0 | H20: =SUM(H21:H22) -> 0 | I20: =SUM(I21:I22) -> 0 | J20: =SUM(J21:J22) -> 0 | K20: =SUM(K21:K22) -> 0 | L20: =SUM(L21:L22) -> 0 | M20: =K20-L20 -> 0
D21: 6041 | E21: Personnel permanent | M21: =K21-L21 -> 0 | N21: =K21/I21 -> #DIV/0!
D22: 6042 | E22: Personnel non permanent | M22: =K22-L22 -> 0 | N22: =K22/I22 -> #DIV/0!
C23: 606 | E23: Charges sociales patronales | F23: =SUM(F24:F28) -> 0 | G23: =SUM(G24:G28) -> 0 | H23: =SUM(H24:H28) -> 0 | I23: =SUM(I24:I28) -> 0 | J23: =SUM(J24:J28) -> 0 | K23: =SUM(K24:K28) -> 0 | L23: =SUM(L24:L28) -> 0 | M23: =K23-L23 -> 0
D24: 6061 | E24: Cotisations à la CNAPS | M24: =K24-L24 -> 0 | N24: =K24/I24 -> #DIV/0!
D25: 6062 | E25: Cotisations caisse de retraites civiles et militaires | M25: =K25-L25 -> 0 | N25: =K25/I25 -> #DIV/0!
D26: 6063 | E26: CPR | M26: =K26-L26 -> 0 | N26: =K26/I26 -> #DIV/0!
D27: 6064 | E27: Cotisations aux OSIE | M27: =K27-L27 -> 0 | N27: =K27/I27 -> #DIV/0!
D28: 6068 | E28: Autres charges sociales patronales | M28: =K28-L28 -> 0 | N28: =K28/I28 -> #DIV/0!
B29: 61 | E29: ACHATS DE BIENS | F29: =SUM(F30,F38,F47,F51,F56) -> 0 | G29: =SUM(G30,G38,G47,G51,G56) -> 0 | H29: =SUM(H30,H38,H47,H51,H56) -> 0 | I29: =SUM(I30,I38,I47,I51,I56) -> 0 | J29: =SUM(J30,J38,J47,J51,J56) -> 0 | K29: =SUM(K30,K38,K47,K51,K56) -> 0 | L29: =SUM(L30,L38,L47,L51,L56) -> 0 | M29: =SUM(M30,M38,M47,M51,M56) -> 0 | N29: =K29/I29 -> #DIV/0!
C30: 611 | E30: Achats de biens de fonctionnement général | F30: =SUM(F31:F37) -> 0 | G30: =SUM(G31:G37) -> 0 | H30: =SUM(H31:H37) -> 0 | I30: =SUM(I31:I37) -> 0 | J30: =SUM(J31:J37) -> 0 | K30: =SUM(K31:K37) -> 0 | L30: =SUM(L31:L37) -> 0 | M30: =K30-L30 -> 0
D31: 6111 | E31: Fournitures et articles de bureau | M31: =K31-L31 -> 0 | N31: =K31/I31 -> #DIV/0!
D32: 6112 | E32: Imprimés, cachets et docuements administratifs | M32: =K32-L32 -> 0 | N32: =K32/I32 -> #DIV/0!
D33: 6113 | E33: Consomptibles informatiques | M33: =K33-L33 -> 0 | N33: =K33/I33 -> #DIV/0!
D34: 6114 | E34: Produits, petits matériels et menues dépenses d'entretien | M34: =K34-L34 -> 0 | N34: =K34/I34 -> #DIV/0!
D35: 6115 | E35: Petits outillages et fournitures d'atelier | M35: =K35-L35 -> 0 | N35: =K35/I35 -> #DIV/0!
D36: 6116 | E36: Instruments spécialisés | M36: =K36-L36 -> 0 | N36: =K36/I36 -> #DIV/0!
D37: 6117 | E37: Habillement | M37: =K37-L37 -> 0 | N37: =K37/I37 -> #DIV/0!
C38: 612 | E38: Achats de biens à usage spécifique | F38: =SUM(F39:F46) -> 0 | G38: =SUM(G39:G46) -> 0 | H38: =SUM(H39:H46) -> 0 | I38: =SUM(I39:I46) -> 0 | J38: =SUM(J39:J46) -> 0 | K38: =SUM(K39:K46) -> 0 | L38: =SUM(L39:L46) -> 0 | M38: =K38-L38 -> 0
D39: 6121 | E39: Fornitures scolaires | M39: =K39-L39 -> 0 | N39: =K39/I39 -> #DIV/0!
D40: 6122 | E40: Consommables médicaux | M40: =K40-L40 -> 0 | N40: =K40/I40 -> #DIV/0!
D41: 6123 | E41: Produits pahrmaceutiques | M41: =K41-L41 -> 0 | N41: =K41/I41 -> #DIV/0!
D42: 6124 | E42: Produits vétérianaires | M42: =K42-L42 -> 0 | N42: =K42/I42 -> #DIV/0!
D43: 6125 | E43: Produits alimentaires | M43: =K43-L43 -> 0 | N43: =K43/I43 -> #DIV/0!
D44: 6126 | E44: Intrants agricoles | M44: =K44-L44 -> 0 | N44: =K44/I44 -> #DIV/0!
D45: 6127 | E45: Fournitures sportives | M45: =K45-L45 -> 0 | N45: =K45/I45 -> #DIV/0!
D46: 6128 | E46: Fournitures ménagères | M46: =K46-L46 -> 0 | N46: =K46/I46 -> #DIV/0!
C47: 613 | E47: Carburants, Lubrifiants et combustibles | F47: =SUM(F48:F50) -> 0 | G47: =SUM(G48:G50) -> 0 | H47: =SUM(H48:H50) -> 0 | I47: =SUM(I48:I50) -> 0 | J47: =SUM(J48:J50) -> 0 | K47: =SUM(K48:K50) -> 0 | L47: =SUM(L48:L50) -> 0 | M47: =K47-L47 -> 0
D48: 6131 | E48: Carburants et Lubrifiants | M48: =K48-L48 -> 0 | N48: =K48/I48 -> #DIV/0!
D49: 6132 | E49: Gaz | M49: =K49-L49 -> 0 | N49: =K49/I49 -> #DIV/0!
D50: 6138 | E50: Autres combustibles | M50: =K50-L50 -> 0 | N50: =K50/I50 -> #DIV/0!
C51: 616 | E51: Variation de stocks | F51: =SUM(F52:F55) -> 0 | G51: =SUM(G52:G55) -> 0 | H51: =SUM(H52:H55) -> 0 | I51: =SUM(I52:I55) -> 0 | J51: =SUM(J52:J55) -> 0 | K51: =SUM(K52:K55) -> 0 | L51: =SUM(L52:L55) -> 0 | M51: =K51-L51 -> 0
D52: 6161 | E52: Variation des stocks de biens de fonctionnement général | M52: =K52-L52 -> 0 | N52: =K52/I52 -> #DIV/0!
D53: 6162 | E53: Variation des stoccks de biens à usage spécifique | M53: =K53-L53 -> 0 | N53: =K53/I53 -> #DIV/0!
D54: 6163 | E54: Variation des stocks de carburants, Lubrifiants et combustibles | M54: =K54-L54 -> 0 | N54: =K54/I54 -> #DIV/0!
D55: 6168 | E55: Variation des staock d'autres achats | M55: =K55-L55 -> 0 | N55: =K55/I55 -> #DIV/0!
C56: 618 | E56: Autres achats | F56: =SUM(F57:F59) -> 0 | G56: =SUM(G57:G59) -> 0 | H56: =SUM(H57:H59) -> 0 | I56: =SUM(I57:I59) -> 0 | J56: =SUM(J57:J59) -> 0 | K56: =SUM(K57:K59) -> 0 | L56: =SUM(L57:L59) -> 0 | M56: =K56-L56 -> 0
D57: 6181 | E57: Achats de matières premières | M57: =K57-L57 -> 0 | N57: =K57/I57 -> #DIV/0!
D58: 6182 | E58: Achats de marchandises destinées à être revendues | M58: =K58-L58 -> 0 | N58: =K58/I58 -> #DIV/0!
D59: 6183 | E59: Emballages | M59: =K59-L59 -> 0 | N59: =K59/I59 -> #DIV/0!
B60: 62 | E60: ACHATS DE SERVICES ET CHARGES PERMANENTES | F60: =SUM(F61,F70,F77,F83,F87,F89,F96,F103) -> 0 | G60: =SUM(G61,G70,G77,G83,G87,G89,G96,G103) -> 0 | H60: =SUM(H61,H70,H77,H83,H87,H89,H96,H103) -> 0 | I60: =SUM(I61,I70,I77,I83,I87,I89,I96,I103) -> 0 | J60: =SUM(J61,J70,J77,J83,J87,J89,J96,J103) -> 0 | K60: =SUM(K61,K70,K77,K83,K87,K89,K96,K103) -> 0 | L60: =SUM(L61,L70,L77,L83,L87,L89,L96,L103) -> 0 | M60: =SUM(M61,M70,M77,M83,M87,M89,M96,M103) -> 0 | N60: =K60/I60 -> #DIV/0!
C61: 621 | E61: Entretien et maintenance | F61: =SUM(F62:F69) -> 0 | G61: =SUM(G62:G69) -> 0 | H61: =SUM(H62:H69) -> 0 | I61: =SUM(I62:I69) -> 0 | J61: =SUM(J62:J69) -> 0 | K61: =SUM(K62:K69) -> 0 | L61: =SUM(L62:L69) -> 0 | M61: =K61-L61 -> 0
D62: 6211 | E62: Entretien de bâtiments | M62: =K62-L62 -> 0 | N62: =K62/I62 -> #DIV/0!
D63: 6212 | E63: Entretien des autres infrastructures | M63: =K63-L63 -> 0 | N63: =K63/I63 -> #DIV/0!
D64: 6213 | E64: Entretien de véhicules | M64: =K64-L64 -> 0 | N64: =K64/I64 -> #DIV/0!
D65: 6214 | E65: Entretien de matériels techniques | M65: =K65-L65 -> 0 | N65: =K65/I65 -> #DIV/0!
D66: 6215 | E66: Entretien et réparation des matériels et mobiliers de bureau | M66: =K66-L66 -> 0 | N66: =K66/I66 -> #DIV/0!
D67: 6216 | E67: Entretien et réparation des matériels et mobiliers de logement | M67: =K67-L67 -> 0 | N67: =K67/I67 -> #DIV/0!
D68: 6217 | E68: Entretien et réparation des matériels et mobiliers scolaires | M68: =K68-L68 -> 0 | N68: =K68/I68 -> #DIV/0!
D69: 6218 | E69: Maintenance du matériel informatique | M69: =K69-L69 -> 0 | N69: =K69/I69 -> #DIV/0!
C70: 622 | E70: Charges de représentation, d'information, de documentation et d'encadrement | F70: =SUM(F71:F76) -> 0 | G70: =SUM(G71:G76) -> 0 | H70: =SUM(H71:H76) -> 0 | I70: =SUM(I71:I76) -> 0 | J70: =SUM(J71:J76) -> 0 | K70: =SUM(K71:K76) -> 0 | L70: =SUM(L71:L76) -> 0 | M70: =K70-L70 -> 0
D71: 6221 | E71: Fêtes et cérémonies officielles | M71: =K71-L71 -> 0 | N71: =K71/I71 -> #DIV/0!
D72: 6222 | E72: Charges de représentation : visites officielles | M72: =K72-L72 -> 0 | N72: =K72/I72 -> #DIV/0!
D73: 6223 | E73: Docuementation et abonnement | M73: =K73-L73 -> 0 | N73: =K73/I73 -> #DIV/0!
D74: 6224 | E74: Impression, reliures, insertions, publicité et promotion | M74: =K74-L74 -> 0 | N74: =K74/I74 -> #DIV/0!
D75: 6225 | E75: Frais de Colloques, séminaires, conférences | M75: =K75-L75 -> 0 | N75: =K75/I75 -> #DIV/0!
D76: 6226 | E76: Foires, exposition | M76: =K76-L76 -> 0 | N76: =K76/I76 -> #DIV/0!
C77: 623 | E77: Charges de transport | F77: =SUM(F78:F82) -> 0 | G77: =SUM(G78:G82) -> 0 | H77: =SUM(H78:H82) -> 0 | I77: =SUM(I78:I82) -> 0 | J77: =SUM(J78:J82) -> 0 | K77: =SUM(K78:K82) -> 0 | L77: =SUM(L78:L82) -> 0 | M77: =K77-L77 -> 0
D78: 6231 | E78: Frais de déplacement intérieur | M78: =K78-L78 -> 0 | N78: =K78/I78 -> #DIV/0!
D79: 6232 | E79: Frais de déplacement extérieur | M79: =K79-L79 -> 0 | N79: =K79/I79 -> #DIV/0!
D80: 6233 | E80: Locations de voitures | M80: =K80-L80 -> 0 | N80: =K80/I80 -> #DIV/0!
D81: 6234 | E81: Transport administratif | M81: =K81-L81 -> 0 | N81: =K81/I81 -> #DIV/0!
D82: 6235 | E82: Transport de bien | M82: =K82-L82 -> 0 | N82: =K82/I82 -> #DIV/0!
C83: 624 | E83: Indemnités de mission | F83: =SUM(F84:F86) -> 0 | G83: =SUM(G84:G86) -> 0 | H83: =SUM(H84:H86) -> 0 | I83: =SUM(I84:I86) -> 0 | J83: =SUM(J84:J86) -> 0 | K83: =SUM(K84:K86) -> 0 | L83: =SUM(L84:L86) -> 0 | M83: =K83-L83 -> 0
D84: 6241 | E84: Indemnité de mission intérieure | M84: =K84-L84 -> 0 | N84: =K84/I84 -> #DIV/0!
D85: 6242 | E85: Indemnité de mission extérieure | M85: =K85-L85 -> 0 | N85: =K85/I85 -> #DIV/0!
D86: 6243 | E86: Viatique | M86: =K86-L86 -> 0 | N86: =K86/I86 -> #DIV/0!
C87: 625 | E87: Eau et éléctricité | F87: =SUM(F88) -> 0 | G87: =SUM(G88) -> 0 | H87: =SUM(H88) -> 0 | I87: =SUM(I88) -> 0 | J87: =SUM(J88) -> 0 | K87: =SUM(K88) -> 0 | L87: =SUM(L88) -> 0 | M87: =K87-L87 -> 0
D88: 6250 | E88: Eau et électricité | M88: =K88-L88 -> 0 | N88: =K88/I88 -> #DIV/0!
C89: 626 | E89: Poste et télécommunications | F89: =SUM(F90:F95) -> 0 | G89: =SUM(G90:G95) -> 0 | H89: =SUM(H90:H95) -> 0 | I89: =SUM(I90:I95) -> 0 | J89: =SUM(J90:J95) -> 0 | K89: =SUM(K90:K95) -> 0 | L89: =SUM(L90:L95) -> 0 | M89: =K89-L89 -> 0
D90: 6261 | E90: Frais postaux | M90: =K90-L90 -> 0 | N90: =K90/I90 -> #DIV/0!
D91: 6262 | E91: Redevances téléphoniques | M91: =K91-L91 -> 0 | N91: =K91/I91 -> #DIV/0!
D92: 6263 | E92: Redevances téléphoniques mobiles | M92: =K92-L92 -> 0 | N92: =K92/I92 -> #DIV/0!
D93: 6264 | E93: Internet | M93: =K93-L93 -> 0 | N93: =K93/I93 -> #DIV/0!
D94: 6265 | E94: Télex | M94: =K94-L94 -> 0 | N94: =K94/I94 -> #DIV/0!
D95: 6268 | E95: Autres | M95: =K95-L95 -> 0 | N95: =K95/I95 -> #DIV/0!
C96: 627 | E96: Charges locatives | F96: =SUM(F97:F102) -> 0 | G96: =SUM(G97:G102) -> 0 | H96: =SUM(H97:H102) -> 0 | I96: =SUM(I97:I102) -> 0 | J96: =SUM(J97:J102) -> 0 | K96: =SUM(K97:K102) -> 0 | L96: =SUM(L97:L102) -> 0 | M96: =K96-L96 -> 0
D97: 6271 | E97: Location d'immeuble de bureau | M97: =K97-L97 -> 0 | N97: =K97/I97 -> #DIV/0!
D98: 6272 | E98: Location d'immeuble de logement | M98: =K98-L98 -> 0 | N98: =K98/I98 -> #DIV/0!
D99: 6273 | E99: Location d'immeuble de bureau-loggement | M99: =K99-L99 -> 0 | N99: =K99/I99 -> #DIV/0!
D100: 6274 | E100: Location de terrain | M100: =K100-L100 -> 0 | N100: =K100/I100 -> #DIV/0!
D101: 6275 | E101: Location de matériels | M101: =K101-L101 -> 0 | N101: =K101/I101 -> #DIV/0!
D102: 6278 | E102: Autres charges locatives | M102: =K102-L102 -> 0 | N102: =K102/I102 -> #DIV/0!
C103: 628 | E103: Services divers | F103: =SUM(F104:F111) -> 0 | G103: =SUM(G104:G111) -> 0 | H103: =SUM(H104:H111) -> 0 | I103: =SUM(I104:I111) -> 0 | J103: =SUM(J104:J111) -> 0 | K103: =SUM(K104:K111) -> 0 | L103: =SUM(L104:L111) -> 0 | M103: =K103-L103 -> 0
D104: 6281 | E104: Rémunérations d'intermédiaires et honoraires | M104: =K104-L104 -> 0 | N104: =K104/I104 -> #DIV/0!
...

Sheet DEPENSES PROGRAMME II
B2: TABLEAU DETAILLE DES DEPENSES
E4: COLLECTIVITE : …..........
E6: PROGRAMME II :
B8: DEPENSES DE FONCTIONNEMENT
B9: COMPTE | E9: INTITULES | F9: BUDGET PRIMITIF | G9: BUDGET ADDITIONNEL | H9: MODIFICATIONS +/- | I9: PREVISIONS DEFINITIVES (1) | J9: ENGAGEMENT | K9: MANDAT ADMIS (2) | L9: PAIEMENT | M9: RESTE A PAYER | N9: TAUX D'EXECUTION (2)/(1)
B10: 60 | E10: CHARGES DE PERSONNEL | F10: =SUM(F11,F14,F17,F20,F23) -> 0 | G10: =SUM(G11,G14,G17,G20,G23) -> 0 | H10: =SUM(H11,H14,H17,H20,H23) -> 0 | I10: =SUM(I11,I14,I17,I20,I23) -> 0 | J10: =SUM(J11,J14,J17,J20,J23) -> 0 | K10: =SUM(K11,K14,K17,K20,K23) -> 0 | L10: =SUM(L11,L14,L17,L20,L23) -> 0 | M10: =SUM(M11,M14,M17,M20,M23) -> 0 | N10: =K10/I10 -> #DIV/0!
C11: 601 | E11: Salaires et accessoires | F11: =SUM(F12:F13) -> 0 | G11: =SUM(G12:G13) -> 0 | H11: =SUM(H12:H13) -> 0 | I11: =SUM(I12:I13) -> 0 | J11: =SUM(J12:J13) -> 0 | K11: =SUM(K12:K13) -> 0 | L11: =SUM(L12:L13) -> 0 | M11: =K11-L11 -> 0
D12: 6011 | E12: Personnel permanent | M12: =K12-L12 -> 0 | N12: =K12/I12 -> #DIV/0!
D13: 6012 | E13: Personnel non permanent | M13: =K13-L13 -> 0 | N13: =K13/I13 -> #DIV/0!
C14: 602 | E14: Indemnités liées à la solde | F14: =SUM(F15:F16) -> 0 | G14: =SUM(G15:G16) -> 0 | H14: =SUM(H15:H16) -> 0 | I14: =SUM(I15:I16) -> 0 | J14: =SUM(J15:J16) -> 0 | K14: =SUM(K15:K16) -> 0 | L14: =SUM(L15:L16) -> 0 | M14: =K14-L14 -> 0
D15: 6021 | E15: Personnel permanent | M15: =K15-L15 -> 0 | N15: =K15/I15 -> #DIV/0!
D16: 6022 | E16: Personnel non permanent | M16: =K16-L16 -> 0 | N16: =K16/I16 -> #DIV/0!
C17: 603 | E17: Indemnités et avantages liés à la fonction | F17: =SUM(F18:F19) -> 0 | G17: =SUM(G18:G19) -> 0 | H17: =SUM(H18:H19) -> 0 | I17: =SUM(I18:I19) -> 0 | J17: =SUM(J18:J19) -> 0 | K17: =SUM(K18:K19) -> 0 | L17: =SUM(L18:L19) -> 0 | M17: =K17-L17 -> 0
D18: 6031 | E18: Personnel permanent | M18: =K18-L18 -> 0 | N18: =K18/I18 -> #DIV/0!
D19: 6032 | E19: Personnel non permanent | M19: =K19-L19 -> 0 | N19: =K19/I19 -> #DIV/0!
C20: 604 | E20: Supplément familial de traitement | F20: =SUM(F21:F22) -> 0 | G20: =SUM(G21:G22) -> 0 | H20: =SUM(H21:H22) -> 0 | I20: =SUM(I21:I22) -> 0 | J20: =SUM(J21:J22) -> 0 | K20: =SUM(K21:K22) -> 0 | L20: =SUM(L21:L22) -> 0 | M20: =K20-L20 -> 0
D21: 6041 | E21: Personnel permanent | M21: =K21-L21 -> 0 | N21: =K21/I21 -> #DIV/0!
D22: 6042 | E22: Personnel non permanent | M22: =K22-L22 -> 0 | N22: =K22/I22 -> #DIV/0!
C23: 606 | E23: Charges sociales patronales | F23: =SUM(F24:F28) -> 0 | G23: =SUM(G24:G28) -> 0 | H23: =SUM(H24:H28) -> 0 | I23: =SUM(I24:I28) -> 0 | J23: =SUM(J24:J28) -> 0 | K23: =SUM(K24:K28) -> 0 | L23: =SUM(L24:L28) -> 0 | M23: =K23-L23 -> 0
D24: 6061 | E24: Cotisations à la CNAPS | M24: =K24-L24 -> 0 | N24: =K24/I24 -> #DIV/0!
D25: 6062 | E25: Cotisations caisse de retraites civiles et militaires | M25: =K25-L25 -> 0 | N25: =K25/I25 -> #DIV/0!
D26: 6063 | E26: CPR | M26: =K26-L26 -> 0 | N26: =K26/I26 -> #DIV/0!
D27: 6064 | E27: Cotisations aux OSIE | M27: =K27-L27 -> 0 | N27: =K27/I27 -> #DIV/0!
D28: 6068 | E28: Autres charges sociales patronales | M28: =K28-L28 -> 0 | N28: =K28/I28 -> #DIV/0!
B29: 61 | E29: ACHATS DE BIENS | F29: =SUM(F30,F38,F47,F51,F56) -> 0 | G29: =SUM(G30,G38,G47,G51,G56) -> 0 | H29: =SUM(H30,H38,H47,H51,H56) -> 0 | I29: =SUM(I30,I38,I47,I51,I56) -> 0 | J29: =SUM(J30,J38,J47,J51,J56) -> 0 | K29: =SUM(K30,K38,K47,K51,K56) -> 0 | L29: =SUM(L30,L38,L47,L51,L56) -> 0 | M29: =SUM(M30,M38,M47,M51,M56) -> 0 | N29: =K29/I29 -> #DIV/0!
C30: 611 | E30: Achats de biens de fonctionnement général | F30: =SUM(F31:F37) -> 0 | G30: =SUM(G31:G37) -> 0 | H30: =SUM(H31:H37) -> 0 | I30: =SUM(I31:I37) -> 0 | J30: =SUM(J31:J37) -> 0 | K30: =SUM(K31:K37) -> 0 | L30: =SUM(L31:L37) -> 0 | M30: =K30-L30 -> 0
D31: 6111 | E31: Fournitures et articles de bureau | M31: =K31-L31 -> 0 | N31: =K31/I31 -> #DIV/0!
D32: 6112 | E32: Imprimés, cachets et docuements administratifs | M32: =K32-L32 -> 0 | N32: =K32/I32 -> #DIV/0!
D33: 6113 | E33: Consomptibles informatiques | M33: =K33-L33 -> 0 | N33: =K33/I33 -> #DIV/0!
D34: 6114 | E34: Produits, petits matériels et menues dépenses d'entretien | M34: =K34-L34 -> 0 | N34: =K34/I34 -> #DIV/0!
D35: 6115 | E35: Petits outillages et fournitures d'atelier | M35: =K35-L35 -> 0 | N35: =K35/I35 -> #DIV/0!
D36: 6116 | E36: Instruments spécialisés | M36: =K36-L36 -> 0 | N36: =K36/I36 -> #DIV/0!
D37: 6117 | E37: Habillement | M37: =K37-L37 -> 0 | N37: =K37/I37 -> #DIV/0!
C38: 612 | E38: Achats de biens à usage spécifique | F38: =SUM(F39:F46) -> 0 | G38: =SUM(G39:G46) -> 0 | H38: =SUM(H39:H46) -> 0 | I38: =SUM(I39:I46) -> 0 | J38: =SUM(J39:J46) -> 0 | K38: =SUM(K39:K46) -> 0 | L38: =SUM(L39:L46) -> 0 | M38: =K38-L38 -> 0
D39: 6121 | E39: Fornitures scolaires | M39: =K39-L39 -> 0 | N39: =K39/I39 -> #DIV/0!
D40: 6122 | E40: Consommables médicaux | M40: =K40-L40 -> 0 | N40: =K40/I40 -> #DIV/0!
D41: 6123 | E41: Produits pahrmaceutiques | M41: =K41-L41 -> 0 | N41: =K41/I41 -> #DIV/0!
D42: 6124 | E42: Produits vétérianaires | M42: =K42-L42 -> 0 | N42: =K42/I42 -> #DIV/0!
D43: 6125 | E43: Produits alimentaires | M43: =K43-L43 -> 0 | N43: =K43/I43 -> #DIV/0!
D44: 6126 | E44: Intrants agricoles | M44: =K44-L44 -> 0 | N44: =K44/I44 -> #DIV/0!
D45: 6127 | E45: Fournitures sportives | M45: =K45-L45 -> 0 | N45: =K45/I45 -> #DIV/0!
D46: 6128 | E46: Fournitures ménagères | M46: =K46-L46 -> 0 | N46: =K46/I46 -> #DIV/0!
C47: 613 | E47: Carburants, Lubrifiants et combustibles | F47: =SUM(F48:F50) -> 0 | G47: =SUM(G48:G50) -> 0 | H47: =SUM(H48:H50) -> 0 | I47: =SUM(I48:I50) -> 0 | J47: =SUM(J48:J50) -> 0 | K47: =SUM(K48:K50) -> 0 | L47: =SUM(L48:L50) -> 0 | M47: =K47-L47 -> 0
D48: 6131 | E48: Carburants et Lubrifiants | M48: =K48-L48 -> 0 | N48: =K48/I48 -> #DIV/0!
D49: 6132 | E49: Gaz | M49: =K49-L49 -> 0 | N49: =K49/I49 -> #DIV/0!
D50: 6138 | E50: Autres combustibles | M50: =K50-L50 -> 0 | N50: =K50/I50 -> #DIV/0!
C51: 616 | E51: Variation de stocks | F51: =SUM(F52:F55) -> 0 | G51: =SUM(G52:G55) -> 0 | H51: =SUM(H52:H55) -> 0 | I51: =SUM(I52:I55) -> 0 | J51: =SUM(J52:J55) -> 0 | K51: =SUM(K52:K55) -> 0 | L51: =SUM(L52:L55) -> 0 | M51: =K51-L51 -> 0
D52: 6161 | E52: Variation des stocks de biens de fonctionnement général | M52: =K52-L52 -> 0 | N52: =K52/I52 -> #DIV/0!
D53: 6162 | E53: Variation des stoccks de biens à usage spécifique | M53: =K53-L53 -> 0 | N53: =K53/I53 -> #DIV/0!
D54: 6163 | E54: Variation des stocks de carburants, Lubrifiants et combustibles | M54: =K54-L54 -> 0 | N54: =K54/I54 -> #DIV/0!
D55: 6168 | E55: Variation des staock d'autres achats | M55: =K55-L55 -> 0 | N55: =K55/I55 -> #DIV/0!
C56: 618 | E56: Autres achats | F56: =SUM(F57:F59) -> 0 | G56: =SUM(G57:G59) -> 0 | H56: =SUM(H57:H59) -> 0 | I56: =SUM(I57:I59) -> 0 | J56: =SUM(J57:J59) -> 0 | K56: =SUM(K57:K59) -> 0 | L56: =SUM(L57:L59) -> 0 | M56: =K56-L56 -> 0
D57: 6181 | E57: Achats de matières premières | M57: =K57-L57 -> 0 | N57: =K57/I57 -> #DIV/0!
D58: 6182 | E58: Achats de marchandises destinées à être revendues | M58: =K58-L58 -> 0 | N58: =K58/I58 -> #DIV/0!
D59: 6183 | E59: Emballages | M59: =K59-L59 -> 0 | N59: =K59/I59 -> #DIV/0!
B60: 62 | E60: ACHATS DE SERVICES ET CHARGES PERMANENTES | F60: =SUM(F61,F70,F77,F83,F87,F89,F96,F103) -> 0 | G60: =SUM(G61,G70,G77,G83,G87,G89,G96,G103) -> 0 | H60: =SUM(H61,H70,H77,H83,H87,H89,H96,H103) -> 0 | I60: =SUM(I61,I70,I77,I83,I87,I89,I96,I103) -> 0 | J60: =SUM(J61,J70,J77,J83,J87,J89,J96,J103) -> 0 | K60: =SUM(K61,K70,K77,K83,K87,K89,K96,K103) -> 0 | L60: =SUM(L61,L70,L77,L83,L87,L89,L96,L103) -> 0 | M60: =SUM(M61,M70,M77,M83,M87,M89,M96,M103) -> 0 | N60: =K60/I60 -> #DIV/0!
C61: 621 | E61: Entretien et maintenance | F61: =SUM(F62:F69) -> 0 | G61: =SUM(G62:G69) -> 0 | H61: =SUM(H62:H69) -> 0 | I61: =SUM(I62:I69) -> 0 | J61: =SUM(J62:J69) -> 0 | K61: =SUM(K62:K69) -> 0 | L61: =SUM(L62:L69) -> 0 | M61: =K61-L61 -> 0
D62: 6211 | E62: Entretien de bâtiments | M62: =K62-L62 -> 0 | N62: =K62/I62 -> #DIV/0!
D63: 6212 | E63: Entretien des autres infrastructures | M63: =K63-L63 -> 0 | N63: =K63/I63 -> #DIV/0!
D64: 6213 | E64: Entretien de véhicules | M64: =K64-L64 -> 0 | N64: =K64/I64 -> #DIV/0!
D65: 6214 | E65: Entretien de matériels techniques | M65: =K65-L65 -> 0 | N65: =K65/I65 -> #DIV/0!
D66: 6215 | E66: Entretien et réparation des matériels et mobiliers de bureau | M66: =K66-L66 -> 0 | N66: =K66/I66 -> #DIV/0!
D67: 6216 | E67: Entretien et réparation des matériels et mobiliers de logement | M67: =K67-L67 -> 0 | N67: =K67/I67 -> #DIV/0!
D68: 6217 | E68: Entretien et réparation des matériels et mobiliers scolaires | M68: =K68-L68 -> 0 | N68: =K68/I68 -> #DIV/0!
D69: 6218 | E69: Maintenance du matériel informatique | M69: =K69-L69 -> 0 | N69: =K69/I69 -> #DIV/0!
C70: 622 | E70: Charges de représentation, d'information, de documentation et d'encadrement | F70: =SUM(F71:F76) -> 0 | G70: =SUM(G71:G76) -> 0 | H70: =SUM(H71:H76) -> 0 | I70: =SUM(I71:I76) -> 0 | J70: =SUM(J71:J76) -> 0 | K70: =SUM(K71:K76) -> 0 | L70: =SUM(L71:L76) -> 0 | M70: =K70-L70 -> 0
D71: 6221 | E71: Fêtes et cérémonies officielles | M71: =K71-L71 -> 0 | N71: =K71/I71 -> #DIV/0!
D72: 6222 | E72: Charges de représentation : visites officielles | M72: =K72-L72 -> 0 | N72: =K72/I72 -> #DIV/0!
D73: 6223 | E73: Docuementation et abonnement | M73: =K73-L73 -> 0 | N73: =K73/I73 -> #DIV/0!
D74: 6224 | E74: Impression, reliures, insertions, publicité et promotion | M74: =K74-L74 -> 0 | N74: =K74/I74 -> #DIV/0!
D75: 6225 | E75: Frais de Colloques, séminaires, conférences | M75: =K75-L75 -> 0 | N75: =K75/I75 -> #DIV/0!
D76: 6226 | E76: Foires, exposition | M76: =K76-L76 -> 0 | N76: =K76/I76 -> #DIV/0!
C77: 623 | E77: Charges de transport | F77: =SUM(F78:F82) -> 0 | G77: =SUM(G78:G82) -> 0 | H77: =SUM(H78:H82) -> 0 | I77: =SUM(I78:I82) -> 0 | J77: =SUM(J78:J82) -> 0 | K77: =SUM(K78:K82) -> 0 | L77: =SUM(L78:L82) -> 0 | M77: =K77-L77 -> 0
D78: 6231 | E78: Frais de déplacement intérieur | M78: =K78-L78 -> 0 | N78: =K78/I78 -> #DIV/0!
D79: 6232 | E79: Frais de déplacement extérieur | M79: =K79-L79 -> 0 | N79: =K79/I79 -> #DIV/0!
D80: 6233 | E80: Locations de voitures | M80: =K80-L80 -> 0 | N80: =K80/I80 -> #DIV/0!
D81: 6234 | E81: Transport administratif | M81: =K81-L81 -> 0 | N81: =K81/I81 -> #DIV/0!
D82: 6235 | E82: Transport de bien | M82: =K82-L82 -> 0 | N82: =K82/I82 -> #DIV/0!
C83: 624 | E83: Indemnités de mission | F83: =SUM(F84:F86) -> 0 | G83: =SUM(G84:G86) -> 0 | H83: =SUM(H84:H86) -> 0 | I83: =SUM(I84:I86) -> 0 | J83: =SUM(J84:J86) -> 0 | K83: =SUM(K84:K86) -> 0 | L83: =SUM(L84:L86) -> 0 | M83: =K83-L83 -> 0
D84: 6241 | E84: Indemnité de mission intérieure | M84: =K84-L84 -> 0 | N84: =K84/I84 -> #DIV/0!
D85: 6242 | E85: Indemnité de mission extérieure | M85: =K85-L85 -> 0 | N85: =K85/I85 -> #DIV/0!
D86: 6243 | E86: Viatique | M86: =K86-L86 -> 0 | N86: =K86/I86 -> #DIV/0!
C87: 625 | E87: Eau et éléctricité | F87: =SUM(F88) -> 0 | G87: =SUM(G88) -> 0 | H87: =SUM(H88) -> 0 | I87: =SUM(I88) -> 0 | J87: =SUM(J88) -> 0 | K87: =SUM(K88) -> 0 | L87: =SUM(L88) -> 0 | M87: =K87-L87 -> 0
D88: 6250 | E88: Eau et électricité | M88: =K88-L88 -> 0 | N88: =K88/I88 -> #DIV/0!
C89: 626 | E89: Poste et télécommunications | F89: =SUM(F90:F95) -> 0 | G89: =SUM(G90:G95) -> 0 | H89: =SUM(H90:H95) -> 0 | I89: =SUM(I90:I95) -> 0 | J89: =SUM(J90:J95) -> 0 | K89: =SUM(K90:K95) -> 0 | L89: =SUM(L90:L95) -> 0 | M89: =K89-L89 -> 0
D90: 6261 | E90: Frais postaux | M90: =K90-L90 -> 0 | N90: =K90/I90 -> #DIV/0!
D91: 6262 | E91: Redevances téléphoniques | M91: =K91-L91 -> 0 | N91: =K91/I91 -> #DIV/0!
D92: 6263 | E92: Redevances téléphoniques mobiles | M92: =K92-L92 -> 0 | N92: =K92/I92 -> #DIV/0!
D93: 6264 | E93: Internet | M93: =K93-L93 -> 0 | N93: =K93/I93 -> #DIV/0!
D94: 6265 | E94: Télex | M94: =K94-L94 -> 0 | N94: =K94/I94 -> #DIV/0!
D95: 6268 | E95: Autres | M95: =K95-L95 -> 0 | N95: =K95/I95 -> #DIV/0!
C96: 627 | E96: Charges locatives | F96: =SUM(F97:F102) -> 0 | G96: =SUM(G97:G102) -> 0 | H96: =SUM(H97:H102) -> 0 | I96: =SUM(I97:I102) -> 0 | J96: =SUM(J97:J102) -> 0 | K96: =SUM(K97:K102) -> 0 | L96: =SUM(L97:L102) -> 0 | M96: =K96-L96 -> 0
D97: 6271 | E97: Location d'immeuble de bureau | M97: =K97-L97 -> 0 | N97: =K97/I97 -> #DIV/0!
D98: 6272 | E98: Location d'immeuble de logement | M98: =K98-L98 -> 0 | N98: =K98/I98 -> #DIV/0!
D99: 6273 | E99: Location d'immeuble de bureau-loggement | M99: =K99-L99 -> 0 | N99: =K99/I99 -> #DIV/0!
D100: 6274 | E100: Location de terrain | M100: =K100-L100 -> 0 | N100: =K100/I100 -> #DIV/0!
D101: 6275 | E101: Location de matériels | M101: =K101-L101 -> 0 | N101: =K101/I101 -> #DIV/0!
D102: 6278 | E102: Autres charges locatives | M102: =K102-L102 -> 0 | N102: =K102/I102 -> #DIV/0!
C103: 628 | E103: Services divers | F103: =SUM(F104:F111) -> 0 | G103: =SUM(G104:G111) -> 0 | H103: =SUM(H104:H111) -> 0 | I103: =SUM(I104:I111) -> 0 | J103: =SUM(J104:J111) -> 0 | K103: =SUM(K104:K111) -> 0 | L103: =SUM(L104:L111) -> 0 | M103: =K103-L103 -> 0
D104: 6281 | E104: Rémunérations d'intermédiaires et honoraires | M104: =K104-L104 -> 0 | N104: =K104/I104 -> #DIV/0!
...

Sheet DEPENSES PROGRAMME III
B2: TABLEAU DETAILLE DES DEPENSES
E4: COLLECTIVITE : …..........
E6: PROGRAMME III :
B8: DEPENSES DE FONCTIONNEMENT
B9: COMPTE | E9: INTITULES | F9: BUDGET PRIMITIF | G9: BUDGET ADDITIONNEL | H9: MODIFICATIONS +/- | I9: PREVISIONS DEFINITIVES (1) | J9: ENGAGEMENT | K9: MANDAT ADMIS (2) | L9: PAIEMENT | M9: RESTE A PAYER | N9: TAUX D'EXECUTION (2)/(1)
B10: 60 | E10: CHARGES DE PERSONNEL | F10: =SUM(F11,F14,F17,F20,F23) -> 0 | G10: =SUM(G11,G14,G17,G20,G23) -> 0 | H10: =SUM(H11,H14,H17,H20,H23) -> 0 | I10: =SUM(I11,I14,I17,I20,I23) -> 0 | J10: =SUM(J11,J14,J17,J20,J23) -> 0 | K10: =SUM(K11,K14,K17,K20,K23) -> 0 | L10: =SUM(L11,L14,L17,L20,L23) -> 0 | M10: =SUM(M11,M14,M17,M20,M23) -> 0 | N10: =K10/I10 -> #DIV/0!
C11: 601 | E11: Salaires et accessoires | F11: =SUM(F12:F13) -> 0 | G11: =SUM(G12:G13) -> 0 | H11: =SUM(H12:H13) -> 0 | I11: =SUM(I12:I13) -> 0 | J11: =SUM(J12:J13) -> 0 | K11: =SUM(K12:K13) -> 0 | L11: =SUM(L12:L13) -> 0 | M11: =K11-L11 -> 0
D12: 6011 | E12: Personnel permanent | M12: =K12-L12 -> 0 | N12: =K12/I12 -> #DIV/0!
D13: 6012 | E13: Personnel non permanent | M13: =K13-L13 -> 0 | N13: =K13/I13 -> #DIV/0!
C14: 602 | E14: Indemnités liées à la solde | F14: =SUM(F15:F16) -> 0 | G14: =SUM(G15:G16) -> 0 | H14: =SUM(H15:H16) -> 0 | I14: =SUM(I15:I16) -> 0 | J14: =SUM(J15:J16) -> 0 | K14: =SUM(K15:K16) -> 0 | L14: =SUM(L15:L16) -> 0 | M14: =K14-L14 -> 0
D15: 6021 | E15: Personnel permanent | M15: =K15-L15 -> 0 | N15: =K15/I15 -> #DIV/0!
D16: 6022 | E16: Personnel non permanent | M16: =K16-L16 -> 0 | N16: =K16/I16 -> #DIV/0!
C17: 603 | E17: Indemnités et avantages liés à la fonction | F17: =SUM(F18:F19) -> 0 | G17: =SUM(G18:G19) -> 0 | H17: =SUM(H18:H19) -> 0 | I17: =SUM(I18:I19) -> 0 | J17: =SUM(J18:J19) -> 0 | K17: =SUM(K18:K19) -> 0 | L17: =SUM(L18:L19) -> 0 | M17: =K17-L17 -> 0
D18: 6031 | E18: Personnel permanent | M18: =K18-L18 -> 0 | N18: =K18/I18 -> #DIV/0!
D19: 6032 | E19: Personnel non permanent | M19: =K19-L19 -> 0 | N19: =K19/I19 -> #DIV/0!
C20: 604 | E20: Supplément familial de traitement | F20: =SUM(F21:F22) -> 0 | G20: =SUM(G21:G22) -> 0 | H20: =SUM(H21:H22) -> 0 | I20: =SUM(I21:I22) -> 0 | J20: =SUM(J21:J22) -> 0 | K20: =SUM(K21:K22) -> 0 | L20: =SUM(L21:L22) -> 0 | M20: =K20-L20 -> 0
D21: 6041 | E21: Personnel permanent | M21: =K21-L21 -> 0 | N21: =K21/I21 -> #DIV/0!
D22: 6042 | E22: Personnel non permanent | M22: =K22-L22 -> 0 | N22: =K22/I22 -> #DIV/0!
C23: 606 | E23: Charges sociales patronales | F23: =SUM(F24:F28) -> 0 | G23: =SUM(G24:G28) -> 0 | H23: =SUM(H24:H28) -> 0 | I23: =SUM(I24:I28) -> 0 | J23: =SUM(J24:J28) -> 0 | K23: =SUM(K24:K28) -> 0 | L23: =SUM(L24:L28) -> 0 | M23: =K23-L23 -> 0
D24: 6061 | E24: Cotisations à la CNAPS | M24: =K24-L24 -> 0 | N24: =K24/I24 -> #DIV/0!
D25: 6062 | E25: Cotisations caisse de retraites civiles et militaires | M25: =K25-L25 -> 0 | N25: =K25/I25 -> #DIV/0!
D26: 6063 | E26: CPR | M26: =K26-L26 -> 0 | N26: =K26/I26 -> #DIV/0!
D27: 6064 | E27: Cotisations aux OSIE | M27: =K27-L27 -> 0 | N27: =K27/I27 -> #DIV/0!
D28: 6068 | E28: Autres charges sociales patronales | M28: =K28-L28 -> 0 | N28: =K28/I28 -> #DIV/0!
B29: 61 | E29: ACHATS DE BIENS | F29: =SUM(F30,F38,F47,F51,F56) -> 0 | G29: =SUM(G30,G38,G47,G51,G56) -> 0 | H29: =SUM(H30,H38,H47,H51,H56) -> 0 | I29: =SUM(I30,I38,I47,I51,I56) -> 0 | J29: =SUM(J30,J38,J47,J51,J56) -> 0 | K29: =SUM(K30,K38,K47,K51,K56) -> 0 | L29: =SUM(L30,L38,L47,L51,L56) -> 0 | M29: =SUM(M30,M38,M47,M51,M56) -> 0 | N29: =K29/I29 -> #DIV/0!
C30: 611 | E30: Achats de biens de fonctionnement général | F30: =SUM(F31:F37) -> 0 | G30: =SUM(G31:G37) -> 0 | H30: =SUM(H31:H37) -> 0 | I30: =SUM(I31:I37) -> 0 | J30: =SUM(J31:J37) -> 0 | K30: =SUM(K31:K37) -> 0 | L30: =SUM(L31:L37) -> 0 | M30: =K30-L30 -> 0
D31: 6111 | E31: Fournitures et articles de bureau | M31: =K31-L31 -> 0 | N31: =K31/I31 -> #DIV/0!
D32: 6112 | E32: Imprimés, cachets et docuements administratifs | M32: =K32-L32 -> 0 | N32: =K32/I32 -> #DIV/0!
D33: 6113 | E33: Consomptibles informatiques | M33: =K33-L33 -> 0 | N33: =K33/I33 -> #DIV/0!
D34: 6114 | E34: Produits, petits matériels et menues dépenses d'entretien | M34: =K34-L34 -> 0 | N34: =K34/I34 -> #DIV/0!
D35: 6115 | E35: Petits outillages et fournitures d'atelier | M35: =K35-L35 -> 0 | N35: =K35/I35 -> #DIV/0!
D36: 6116 | E36: Instruments spécialisés | M36: =K36-L36 -> 0 | N36: =K36/I36 -> #DIV/0!
D37: 6117 | E37: Habillement | M37: =K37-L37 -> 0 | N37: =K37/I37 -> #DIV/0!
C38: 612 | E38: Achats de biens à usage spécifique | F38: =SUM(F39:F46) -> 0 | G38: =SUM(G39:G46) -> 0 | H38: =SUM(H39:H46) -> 0 | I38: =SUM(I39:I46) -> 0 | J38: =SUM(J39:J46) -> 0 | K38: =SUM(K39:K46) -> 0 | L38: =SUM(L39:L46) -> 0 | M38: =K38-L38 -> 0
D39: 6121 | E39: Fornitures scolaires | M39: =K39-L39 -> 0 | N39: =K39/I39 -> #DIV/0!
D40: 6122 | E40: Consommables médicaux | M40: =K40-L40 -> 0 | N40: =K40/I40 -> #DIV/0!
D41: 6123 | E41: Produits pahrmaceutiques | M41: =K41-L41 -> 0 | N41: =K41/I41 -> #DIV/0!
D42: 6124 | E42: Produits vétérianaires | M42: =K42-L42 -> 0 | N42: =K42/I42 -> #DIV/0!
D43: 6125 | E43: Produits alimentaires | M43: =K43-L43 -> 0 | N43: =K43/I43 -> #DIV/0!
D44: 6126 | E44: Intrants agricoles | M44: =K44-L44 -> 0 | N44: =K44/I44 -> #DIV/0!
D45: 6127 | E45: Fournitures sportives | M45: =K45-L45 -> 0 | N45: =K45/I45 -> #DIV/0!
D46: 6128 | E46: Fournitures ménagères | M46: =K46-L46 -> 0 | N46: =K46/I46 -> #DIV/0!
C47: 613 | E47: Carburants, Lubrifiants et combustibles | F47: =SUM(F48:F50) -> 0 | G47: =SUM(G48:G50) -> 0 | H47: =SUM(H48:H50) -> 0 | I47: =SUM(I48:I50) -> 0 | J47: =SUM(J48:J50) -> 0 | K47: =SUM(K48:K50) -> 0 | L47: =SUM(L48:L50) -> 0 | M47: =K47-L47 -> 0
D48: 6131 | E48: Carburants et Lubrifiants | M48: =K48-L48 -> 0 | N48: =K48/I48 -> #DIV/0!
D49: 6132 | E49: Gaz | M49: =K49-L49 -> 0 | N49: =K49/I49 -> #DIV/0!
D50: 6138 | E50: Autres combustibles | M50: =K50-L50 -> 0 | N50: =K50/I50 -> #DIV/0!
C51: 616 | E51: Variation de stocks | F51: =SUM(F52:F55) -> 0 | G51: =SUM(G52:G55) -> 0 | H51: =SUM(H52:H55) -> 0 | I51: =SUM(I52:I55) -> 0 | J51: =SUM(J52:J55) -> 0 | K51: =SUM(K52:K55) -> 0 | L51: =SUM(L52:L55) -> 0 | M51: =K51-L51 -> 0
D52: 6161 | E52: Variation des stocks de biens de fonctionnement général | M52: =K52-L52 -> 0 | N52: =K52/I52 -> #DIV/0!
D53: 6162 | E53: Variation des stoccks de biens à usage spécifique | M53: =K53-L53 -> 0 | N53: =K53/I53 -> #DIV/0!
D54: 6163 | E54: Variation des stocks de carburants, Lubrifiants et combustibles | M54: =K54-L54 -> 0 | N54: =K54/I54 -> #DIV/0!
D55: 6168 | E55: Variation des staock d'autres achats | M55: =K55-L55 -> 0 | N55: =K55/I55 -> #DIV/0!
C56: 618 | E56: Autres achats | F56: =SUM(F57:F59) -> 0 | G56: =SUM(G57:G59) -> 0 | H56: =SUM(H57:H59) -> 0 | I56: =SUM(I57:I59) -> 0 | J56: =SUM(J57:J59) -> 0 | K56: =SUM(K57:K59) -> 0 | L56: =SUM(L57:L59) -> 0 | M56: =K56-L56 -> 0
D57: 6181 | E57: Achats de matières premières | M57: =K57-L57 -> 0 | N57: =K57/I57 -> #DIV/0!
D58: 6182 | E58: Achats de marchandises destinées à être revendues | M58: =K58-L58 -> 0 | N58: =K58/I58 -> #DIV/0!
D59: 6183 | E59: Emballages | M59: =K59-L59 -> 0 | N59: =K59/I59 -> #DIV/0!
B60: 62 | E60: ACHATS DE SERVICES ET CHARGES PERMANENTES | F60: =SUM(F61,F70,F77,F83,F87,F89,F96,F103) -> 0 | G60: =SUM(G61,G70,G77,G83,G87,G89,G96,G103) -> 0 | H60: =SUM(H61,H70,H77,H83,H87,H89,H96,H103) -> 0 | I60: =SUM(I61,I70,I77,I83,I87,I89,I96,I103) -> 0 | J60: =SUM(J61,J70,J77,J83,J87,J89,J96,J103) -> 0 | K60: =SUM(K61,K70,K77,K83,K87,K89,K96,K103) -> 0 | L60: =SUM(L61,L70,L77,L83,L87,L89,L96,L103) -> 0 | M60: =SUM(M61,M70,M77,M83,M87,M89,M96,M103) -> 0 | N60: =K60/I60 -> #DIV/0!
C61: 621 | E61: Entretien et maintenance | F61: =SUM(F62:F69) -> 0 | G61: =SUM(G62:G69) -> 0 | H61: =SUM(H62:H69) -> 0 | I61: =SUM(I62:I69) -> 0 | J61: =SUM(J62:J69) -> 0 | K61: =SUM(K62:K69) -> 0 | L61: =SUM(L62:L69) -> 0 | M61: =K61-L61 -> 0
D62: 6211 | E62: Entretien de bâtiments | M62: =K62-L62 -> 0 | N62: =K62/I62 -> #DIV/0!
D63: 6212 | E63: Entretien des autres infrastructures | M63: =K63-L63 -> 0 | N63: =K63/I63 -> #DIV/0!
D64: 6213 | E64: Entretien de véhicules | M64: =K64-L64 -> 0 | N64: =K64/I64 -> #DIV/0!
D65: 6214 | E65: Entretien de matériels techniques | M65: =K65-L65 -> 0 | N65: =K65/I65 -> #DIV/0!
D66: 6215 | E66: Entretien et réparation des matériels et mobiliers de bureau | M66: =K66-L66 -> 0 | N66: =K66/I66 -> #DIV/0!
D67: 6216 | E67: Entretien et réparation des matériels et mobiliers de logement | M67: =K67-L67 -> 0 | N67: =K67/I67 -> #DIV/0!
D68: 6217 | E68: Entretien et réparation des matériels et mobiliers scolaires | M68: =K68-L68 -> 0 | N68: =K68/I68 -> #DIV/0!
D69: 6218 | E69: Maintenance du matériel informatique | M69: =K69-L69 -> 0 | N69: =K69/I69 -> #DIV/0!
C70: 622 | E70: Charges de représentation, d'information, de documentation et d'encadrement | F70: =SUM(F71:F76) -> 0 | G70: =SUM(G71:G76) -> 0 | H70: =SUM(H71:H76) -> 0 | I70: =SUM(I71:I76) -> 0 | J70: =SUM(J71:J76) -> 0 | K70: =SUM(K71:K76) -> 0 | L70: =SUM(L71:L76) -> 0 | M70: =K70-L70 -> 0
D71: 6221 | E71: Fêtes et cérémonies officielles | M71: =K71-L71 -> 0 | N71: =K71/I71 -> #DIV/0!
D72: 6222 | E72: Charges de représentation : visites officielles | M72: =K72-L72 -> 0 | N72: =K72/I72 -> #DIV/0!
D73: 6223 | E73: Docuementation et abonnement | M73: =K73-L73 -> 0 | N73: =K73/I73 -> #DIV/0!
D74: 6224 | E74: Impression, reliures, insertions, publicité et promotion | M74: =K74-L74 -> 0 | N74: =K74/I74 -> #DIV/0!
D75: 6225 | E75: Frais de Colloques, séminaires, conférences | M75: =K75-L75 -> 0 | N75: =K75/I75 -> #DIV/0!
D76: 6226 | E76: Foires, exposition | M76: =K76-L76 -> 0 | N76: =K76/I76 -> #DIV/0!
C77: 623 | E77: Charges de transport | F77: =SUM(F78:F82) -> 0 | G77: =SUM(G78:G82) -> 0 | H77: =SUM(H78:H82) -> 0 | I77: =SUM(I78:I82) -> 0 | J77: =SUM(J78:J82) -> 0 | K77: =SUM(K78:K82) -> 0 | L77: =SUM(L78:L82) -> 0 | M77: =K77-L77 -> 0
D78: 6231 | E78: Frais de déplacement intérieur | M78: =K78-L78 -> 0 | N78: =K78/I78 -> #DIV/0!
D79: 6232 | E79: Frais de déplacement extérieur | M79: =K79-L79 -> 0 | N79: =K79/I79 -> #DIV/0!
D80: 6233 | E80: Locations de voitures | M80: =K80-L80 -> 0 | N80: =K80/I80 -> #DIV/0!
D81: 6234 | E81: Transport administratif | M81: =K81-L81 -> 0 | N81: =K81/I81 -> #DIV/0!
D82: 6235 | E82: Transport de bien | M82: =K82-L82 -> 0 | N82: =K82/I82 -> #DIV/0!
C83: 624 | E83: Indemnités de mission | F83: =SUM(F84:F86) -> 0 | G83: =SUM(G84:G86) -> 0 | H83: =SUM(H84:H86) -> 0 | I83: =SUM(I84:I86) -> 0 | J83: =SUM(J84:J86) -> 0 | K83: =SUM(K84:K86) -> 0 | L83: =SUM(L84:L86) -> 0 | M83: =K83-L83 -> 0
D84: 6241 | E84: Indemnité de mission intérieure | M84: =K84-L84 -> 0 | N84: =K84/I84 -> #DIV/0!
D85: 6242 | E85: Indemnité de mission extérieure | M85: =K85-L85 -> 0 | N85: =K85/I85 -> #DIV/0!
D86: 6243 | E86: Viatique | M86: =K86-L86 -> 0 | N86: =K86/I86 -> #DIV/0!
C87: 625 | E87: Eau et éléctricité | F87: =SUM(F88) -> 0 | G87: =SUM(G88) -> 0 | H87: =SUM(H88) -> 0 | I87: =SUM(I88) -> 0 | J87: =SUM(J88) -> 0 | K87: =SUM(K88) -> 0 | L87: =SUM(L88) -> 0 | M87: =K87-L87 -> 0
D88: 6250 | E88: Eau et électricité | M88: =K88-L88 -> 0 | N88: =K88/I88 -> #DIV/0!
C89: 626 | E89: Poste et télécommunications | F89: =SUM(F90:F95) -> 0 | G89: =SUM(G90:G95) -> 0 | H89: =SUM(H90:H95) -> 0 | I89: =SUM(I90:I95) -> 0 | J89: =SUM(J90:J95) -> 0 | K89: =SUM(K90:K95) -> 0 | L89: =SUM(L90:L95) -> 0 | M89: =K89-L89 -> 0
D90: 6261 | E90: Frais postaux | M90: =K90-L90 -> 0 | N90: =K90/I90 -> #DIV/0!
D91: 6262 | E91: Redevances téléphoniques | M91: =K91-L91 -> 0 | N91: =K91/I91 -> #DIV/0!
D92: 6263 | E92: Redevances téléphoniques mobiles | M92: =K92-L92 -> 0 | N92: =K92/I92 -> #DIV/0!
D93: 6264 | E93: Internet | M93: =K93-L93 -> 0 | N93: =K93/I93 -> #DIV/0!
D94: 6265 | E94: Télex | M94: =K94-L94 -> 0 | N94: =K94/I94 -> #DIV/0!
D95: 6268 | E95: Autres | M95: =K95-L95 -> 0 | N95: =K95/I95 -> #DIV/0!
C96: 627 | E96: Charges locatives | F96: =SUM(F97:F102) -> 0 | G96: =SUM(G97:G102) -> 0 | H96: =SUM(H97:H102) -> 0 | I96: =SUM(I97:I102) -> 0 | J96: =SUM(J97:J102) -> 0 | K96: =SUM(K97:K102) -> 0 | L96: =SUM(L97:L102) -> 0 | M96: =K96-L96 -> 0
D97: 6271 | E97: Location d'immeuble de bureau | M97: =K97-L97 -> 0 | N97: =K97/I97 -> #DIV/0!
D98: 6272 | E98: Location d'immeuble de logement | M98: =K98-L98 -> 0 | N98: =K98/I98 -> #DIV/0!
D99: 6273 | E99: Location d'immeuble de bureau-loggement | M99: =K99-L99 -> 0 | N99: =K99/I99 -> #DIV/0!
D100: 6274 | E100: Location de terrain | M100: =K100-L100 -> 0 | N100: =K100/I100 -> #DIV/0!
D101: 6275 | E101: Location de matériels | M101: =K101-L101 -> 0 | N101: =K101/I101 -> #DIV/0!
D102: 6278 | E102: Autres charges locatives | M102: =K102-L102 -> 0 | N102: =K102/I102 -> #DIV/0!
C103: 628 | E103: Services divers | F103: =SUM(F104:F111) -> 0 | G103: =SUM(G104:G111) -> 0 | H103: =SUM(H104:H111) -> 0 | I103: =SUM(I104:I111) -> 0 | J103: =SUM(J104:J111) -> 0 | K103: =SUM(K104:K111) -> 0 | L103: =SUM(L104:L111) -> 0 | M103: =K103-L103 -> 0
D104: 6281 | E104: Rémunérations d'intermédiaires et honoraires | M104: =K104-L104 -> 0 | N104: =K104/I104 -> #DIV/0!
...

Sheet RECAP DEPENSES PAR PROGRAMME
B2: RECAPITULATIF DES DEPENSES PAR PROGRAMME
E4: COLLECTIVITE : …..........
B7: DEPENSES DE FONCTIONNEMENT
F8: MANDATEMENT | J8: PAIEMENT | N8: RESTE A PAYER
B9: COMPTE | E9: INTITULES | F9: PROGRAMME I | G9: PROGRAMME II | H9: PROGRAMME III | I9: TOTAL | J9: PROGRAMME I | K9: PROGRAMME II | L9: PROGRAMME III | M9: TOTAL | N9: PROGRAMME I | O9: PROGRAMME II | P9: PROGRAMME III | Q9: TOTAL
B10: 60 | E10: CHARGES DE PERSONNEL | F10: =SUM(F11,F14,F17,F20,F23) -> 0 | G10: =SUM(G11,G14,G17,G20,G23) -> 0 | H10: =SUM(H11,H14,H17,H20,H23) -> 0 | I10: =SUM(F10,G10,H10) -> 0 | J10: =SUM(J11,J14,J17,J20,J23) -> 0 | K10: =SUM(K11,K14,K17,K20,K23) -> 0 | L10: =SUM(L11,L14,L17,L20,L23) -> 0 | M10: =SUM(J10,K10,L10) -> 0 | N10: =SUM(N11,N14,N17,N20,N23) -> 0 | O10: =SUM(O11,O14,O17,O20,O23) -> 0 | P10: =SUM(P11,P14,P17,P20,P23) -> 0 | Q10: =SUM(N10,O10,P10) -> 0
C11: 601 | E11: Salaires et accessoires | F11: =SUM(F12:F13) -> 0 | G11: =SUM(G12:G13) -> 0 | H11: =SUM(H12:H13) -> 0 | J11: =SUM(J12:J13) -> 0 | K11: =SUM(K12:K13) -> 0 | L11: =SUM(L12:L13) -> 0 | N11: =SUM(N12:N13) -> 0 | O11: =SUM(O12:O13) -> 0 | P11: =SUM(P12:P13) -> 0
D12: 6011 | E12: Personnel permanent | F12: ='DEPENSES PROGRAMME I'!K12 -> 0 | G12: ='DEPENSES PROGRAMME II'!K12 -> 0 | H12: ='DEPENSES PROGRAMME III'!K12 -> 0 | J12: ='DEPENSES PROGRAMME I'!L12 -> 0 | K12: ='DEPENSES PROGRAMME II'!L12 -> 0 | L12: ='DEPENSES PROGRAMME III'!L12 -> 0 | N12: ='DEPENSES PROGRAMME I'!M12 -> 0 | O12: ='DEPENSES PROGRAMME II'!M12 -> 0 | P12: ='DEPENSES PROGRAMME III'!M12 -> 0
D13: 6012 | E13: Personnel non permanent | F13: ='DEPENSES PROGRAMME I'!K13 -> 0 | G13: ='DEPENSES PROGRAMME II'!K13 -> 0 | H13: ='DEPENSES PROGRAMME III'!K13 -> 0 | J13: ='DEPENSES PROGRAMME I'!L13 -> 0 | K13: ='DEPENSES PROGRAMME II'!L13 -> 0 | L13: ='DEPENSES PROGRAMME III'!L13 -> 0 | N13: ='DEPENSES PROGRAMME I'!M13 -> 0 | O13: ='DEPENSES PROGRAMME II'!M13 -> 0 | P13: ='DEPENSES PROGRAMME III'!M13 -> 0
C14: 602 | E14: Indemnités liées à la solde | F14: =SUM(F15:F16) -> 0 | G14: =SUM(G15:G16) -> 0 | H14: =SUM(H15:H16) -> 0 | J14: =SUM(J15:J16) -> 0 | K14: =SUM(K15:K16) -> 0 | L14: =SUM(L15:L16) -> 0 | N14: =SUM(N15:N16) -> 0 | O14: =SUM(O15:O16) -> 0 | P14: =SUM(P15:P16) -> 0
D15: 6021 | E15: Personnel permanent | F15: ='DEPENSES PROGRAMME I'!K15 -> 0 | G15: ='DEPENSES PROGRAMME II'!K15 -> 0 | H15: ='DEPENSES PROGRAMME III'!K15 -> 0 | J15: ='DEPENSES PROGRAMME I'!L15 -> 0 | K15: ='DEPENSES PROGRAMME II'!L15 -> 0 | L15: ='DEPENSES PROGRAMME III'!L15 -> 0 | N15: ='DEPENSES PROGRAMME I'!M15 -> 0 | O15: ='DEPENSES PROGRAMME II'!M15 -> 0 | P15: ='DEPENSES PROGRAMME III'!M15 -> 0
D16: 6022 | E16: Personnel non permanent | F16: ='DEPENSES PROGRAMME I'!K16 -> 0 | G16: ='DEPENSES PROGRAMME II'!K16 -> 0 | H16: ='DEPENSES PROGRAMME III'!K16 -> 0 | J16: ='DEPENSES PROGRAMME I'!L16 -> 0 | K16: ='DEPENSES PROGRAMME II'!L16 -> 0 | L16: ='DEPENSES PROGRAMME III'!L16 -> 0 | N16: ='DEPENSES PROGRAMME I'!M16 -> 0 | O16: ='DEPENSES PROGRAMME II'!M16 -> 0 | P16: ='DEPENSES PROGRAMME III'!M16 -> 0
C17: 603 | E17: Indemnités et avantages liés à la fonction | F17: =SUM(F18:F19) -> 0 | G17: =SUM(G18:G19) -> 0 | H17: =SUM(H18:H19) -> 0 | J17: =SUM(J18:J19) -> 0 | K17: =SUM(K18:K19) -> 0 | L17: =SUM(L18:L19) -> 0 | N17: =SUM(N18:N19) -> 0 | O17: =SUM(O18:O19) -> 0 | P17: =SUM(P18:P19) -> 0
D18: 6031 | E18: Personnel permanent | F18: ='DEPENSES PROGRAMME I'!K18 -> 0 | G18: ='DEPENSES PROGRAMME II'!K18 -> 0 | H18: ='DEPENSES PROGRAMME III'!K18 -> 0 | J18: ='DEPENSES PROGRAMME I'!L18 -> 0 | K18: ='DEPENSES PROGRAMME II'!L18 -> 0 | L18: ='DEPENSES PROGRAMME III'!L18 -> 0 | N18: ='DEPENSES PROGRAMME I'!M18 -> 0 | O18: ='DEPENSES PROGRAMME II'!M18 -> 0 | P18: ='DEPENSES PROGRAMME III'!M18 -> 0
D19: 6032 | E19: Personnel non permanent | F19: ='DEPENSES PROGRAMME I'!K19 -> 0 | G19: ='DEPENSES PROGRAMME II'!K19 -> 0 | H19: ='DEPENSES PROGRAMME III'!K19 -> 0 | J19: ='DEPENSES PROGRAMME I'!L19 -> 0 | K19: ='DEPENSES PROGRAMME II'!L19 -> 0 | L19: ='DEPENSES PROGRAMME III'!L19 -> 0 | N19: ='DEPENSES PROGRAMME I'!M19 -> 0 | O19: ='DEPENSES PROGRAMME II'!M19 -> 0 | P19: ='DEPENSES PROGRAMME III'!M19 -> 0
C20: 604 | E20: Supplément familial de traitement | F20: =SUM(F21:F22) -> 0 | G20: =SUM(G21:G22) -> 0 | H20: =SUM(H21:H22) -> 0 | J20: =SUM(J21:J22) -> 0 | K20: =SUM(K21:K22) -> 0 | L20: =SUM(L21:L22) -> 0 | N20: =SUM(N21:N22) -> 0 | O20: =SUM(O21:O22) -> 0 | P20: =SUM(P21:P22) -> 0
D21: 6041 | E21: Personnel permanent | F21: ='DEPENSES PROGRAMME I'!K21 -> 0 | G21: ='DEPENSES PROGRAMME II'!K21 -> 0 | H21: ='DEPENSES PROGRAMME III'!K21 -> 0 | J21: ='DEPENSES PROGRAMME I'!L21 -> 0 | K21: ='DEPENSES PROGRAMME II'!L21 -> 0 | L21: ='DEPENSES PROGRAMME III'!L21 -> 0 | N21: ='DEPENSES PROGRAMME I'!M21 -> 0 | O21: ='DEPENSES PROGRAMME II'!M21 -> 0 | P21: ='DEPENSES PROGRAMME III'!M21 -> 0
D22: 6042 | E22: Personnel non permanent | F22: ='DEPENSES PROGRAMME I'!K22 -> 0 | G22: ='DEPENSES PROGRAMME II'!K22 -> 0 | H22: ='DEPENSES PROGRAMME III'!K22 -> 0 | J22: ='DEPENSES PROGRAMME I'!L22 -> 0 | K22: ='DEPENSES PROGRAMME II'!L22 -> 0 | L22: ='DEPENSES PROGRAMME III'!L22 -> 0 | N22: ='DEPENSES PROGRAMME I'!M22 -> 0 | O22: ='DEPENSES PROGRAMME II'!M22 -> 0 | P22: ='DEPENSES PROGRAMME III'!M22 -> 0
C23: 606 | E23: Charges sociales patronales | F23: =SUM(F24:F28) -> 0 | G23: =SUM(G24:G28) -> 0 | H23: =SUM(H24:H28) -> 0 | J23: =SUM(J24:J28) -> 0 | K23: =SUM(K24:K28) -> 0 | L23: =SUM(L24:L28) -> 0 | N23: =SUM(N24:N28) -> 0 | O23: =SUM(O24:O28) -> 0 | P23: =SUM(P24:P28) -> 0
D24: 6061 | E24: Cotisations à la CNAPS | F24: ='DEPENSES PROGRAMME I'!K24 -> 0 | G24: ='DEPENSES PROGRAMME II'!K24 -> 0 | H24: ='DEPENSES PROGRAMME III'!K24 -> 0 | J24: ='DEPENSES PROGRAMME I'!L24 -> 0 | K24: ='DEPENSES PROGRAMME II'!L24 -> 0 | L24: ='DEPENSES PROGRAMME III'!L24 -> 0 | N24: ='DEPENSES PROGRAMME I'!M24 -> 0 | O24: ='DEPENSES PROGRAMME II'!M24 -> 0 | P24: ='DEPENSES PROGRAMME III'!M24 -> 0
D25: 6062 | E25: Cotisations caisse de retraites civiles et militaires | F25: ='DEPENSES PROGRAMME I'!K25 -> 0 | G25: ='DEPENSES PROGRAMME II'!K25 -> 0 | H25: ='DEPENSES PROGRAMME III'!K25 -> 0 | J25: ='DEPENSES PROGRAMME I'!L25 -> 0 | K25: ='DEPENSES PROGRAMME II'!L25 -> 0 | L25: ='DEPENSES PROGRAMME III'!L25 -> 0 | N25: ='DEPENSES PROGRAMME I'!M25 -> 0 | O25: ='DEPENSES PROGRAMME II'!M25 -> 0 | P25: ='DEPENSES PROGRAMME III'!M25 -> 0
D26: 6063 | E26: CPR | F26: ='DEPENSES PROGRAMME I'!K26 -> 0 | G26: ='DEPENSES PROGRAMME II'!K26 -> 0 | H26: ='DEPENSES PROGRAMME III'!K26 -> 0 | J26: ='DEPENSES PROGRAMME I'!L26 -> 0 | K26: ='DEPENSES PROGRAMME II'!L26 -> 0 | L26: ='DEPENSES PROGRAMME III'!L26 -> 0 | N26: ='DEPENSES PROGRAMME I'!M26 -> 0 | O26: ='DEPENSES PROGRAMME II'!M26 -> 0 | P26: ='DEPENSES PROGRAMME III'!M26 -> 0
D27: 6064 | E27: Cotisations aux OSIE | F27: ='DEPENSES PROGRAMME I'!K27 -> 0 | G27: ='DEPENSES PROGRAMME II'!K27 -> 0 | H27: ='DEPENSES PROGRAMME III'!K27 -> 0 | J27: ='DEPENSES PROGRAMME I'!L27 -> 0 | K27: ='DEPENSES PROGRAMME II'!L27 -> 0 | L27: ='DEPENSES PROGRAMME III'!L27 -> 0 | N27: ='DEPENSES PROGRAMME I'!M27 -> 0 | O27: ='DEPENSES PROGRAMME II'!M27 -> 0 | P27: ='DEPENSES PROGRAMME III'!M27 -> 0
D28: 6068 | E28: Autres charges sociales patronales | F28: ='DEPENSES PROGRAMME I'!K28 -> 0 | G28: ='DEPENSES PROGRAMME II'!K28 -> 0 | H28: ='DEPENSES PROGRAMME III'!K28 -> 0 | J28: ='DEPENSES PROGRAMME I'!L28 -> 0 | K28: ='DEPENSES PROGRAMME II'!L28 -> 0 | L28: ='DEPENSES PROGRAMME III'!L28 -> 0 | N28: ='DEPENSES PROGRAMME I'!M28 -> 0 | O28: ='DEPENSES PROGRAMME II'!M28 -> 0 | P28: ='DEPENSES PROGRAMME III'!M28 -> 0
B29: 61 | E29: ACHATS DE BIENS | F29: =SUM(F30,F38,F47,F51,F56) -> 0 | G29: =SUM(G30,G38,G47,G51,G56) -> 0 | H29: =SUM(H30,H38,H47,H51,H56) -> 0 | I29: =SUM(F29,G29,H29) -> 0 | J29: =SUM(J30,J38,J47,J51,J56) -> 0 | K29: =SUM(K30,K38,K47,K51,K56) -> 0 | L29: =SUM(L30,L38,L47,L51,L56) -> 0 | M29: =SUM(J29,K29,L29) -> 0 | N29: =SUM(N30,N38,N47,N51,N56) -> 0 | O29: =SUM(O30,O38,O47,O51,O56) -> 0 | P29: =SUM(P30,P38,P47,P51,P56) -> 0 | Q29: =SUM(N29,O29,P29) -> 0
C30: 611 | E30: Achats de biens de fonctionnement général | F30: =SUM(F31:F37) -> 0 | G30: =SUM(G31:G37) -> 0 | H30: =SUM(H31:H37) -> 0 | J30: =SUM(J31:J37) -> 0 | K30: =SUM(K31:K37) -> 0 | L30: =SUM(L31:L37) -> 0 | N30: =SUM(N31:N37) -> 0 | O30: =SUM(O31:O37) -> 0 | P30: =SUM(P31:P37) -> 0
D31: 6111 | E31: Fournitures et articles de bureau | F31: ='DEPENSES PROGRAMME I'!K31 -> 0 | G31: ='DEPENSES PROGRAMME II'!K31 -> 0 | H31: ='DEPENSES PROGRAMME III'!K31 -> 0 | J31: ='DEPENSES PROGRAMME I'!L31 -> 0 | K31: ='DEPENSES PROGRAMME II'!L31 -> 0 | L31: ='DEPENSES PROGRAMME III'!L31 -> 0 | N31: ='DEPENSES PROGRAMME I'!M31 -> 0 | O31: ='DEPENSES PROGRAMME II'!M31 -> 0 | P31: ='DEPENSES PROGRAMME III'!M31 -> 0
D32: 6112 | E32: Imprimés, cachets et docuements administratifs | F32: ='DEPENSES PROGRAMME I'!K32 -> 0 | G32: ='DEPENSES PROGRAMME II'!K32 -> 0 | H32: ='DEPENSES PROGRAMME III'!K32 -> 0 | J32: ='DEPENSES PROGRAMME I'!L32 -> 0 | K32: ='DEPENSES PROGRAMME II'!L32 -> 0 | L32: ='DEPENSES PROGRAMME III'!L32 -> 0 | N32: ='DEPENSES PROGRAMME I'!M32 -> 0 | O32: ='DEPENSES PROGRAMME II'!M32 -> 0 | P32: ='DEPENSES PROGRAMME III'!M32 -> 0
D33: 6113 | E33: Consomptibles informatiques | F33: ='DEPENSES PROGRAMME I'!K33 -> 0 | G33: ='DEPENSES PROGRAMME II'!K33 -> 0 | H33: ='DEPENSES PROGRAMME III'!K33 -> 0 | J33: ='DEPENSES PROGRAMME I'!L33 -> 0 | K33: ='DEPENSES PROGRAMME II'!L33 -> 0 | L33: ='DEPENSES PROGRAMME III'!L33 -> 0 | N33: ='DEPENSES PROGRAMME I'!M33 -> 0 | O33: ='DEPENSES PROGRAMME II'!M33 -> 0 | P33: ='DEPENSES PROGRAMME III'!M33 -> 0
D34: 6114 | E34: Produits, petits matériels et menues dépenses d'entretien | F34: ='DEPENSES PROGRAMME I'!K34 -> 0 | G34: ='DEPENSES PROGRAMME II'!K34 -> 0 | H34: ='DEPENSES PROGRAMME III'!K34 -> 0 | J34: ='DEPENSES PROGRAMME I'!L34 -> 0 | K34: ='DEPENSES PROGRAMME II'!L34 -> 0 | L34: ='DEPENSES PROGRAMME III'!L34 -> 0 | N34: ='DEPENSES PROGRAMME I'!M34 -> 0 | O34: ='DEPENSES PROGRAMME II'!M34 -> 0 | P34: ='DEPENSES PROGRAMME III'!M34 -> 0
D35: 6115 | E35: Petits outillages et fournitures d'atelier | F35: ='DEPENSES PROGRAMME I'!K35 -> 0 | G35: ='DEPENSES PROGRAMME II'!K35 -> 0 | H35: ='DEPENSES PROGRAMME III'!K35 -> 0 | J35: ='DEPENSES PROGRAMME I'!L35 -> 0 | K35: ='DEPENSES PROGRAMME II'!L35 -> 0 | L35: ='DEPENSES PROGRAMME III'!L35 -> 0 | N35: ='DEPENSES PROGRAMME I'!M35 -> 0 | O35: ='DEPENSES PROGRAMME II'!M35 -> 0 | P35: ='DEPENSES PROGRAMME III'!M35 -> 0
D36: 6116 | E36: Instruments spécialisés | F36: ='DEPENSES PROGRAMME I'!K36 -> 0 | G36: ='DEPENSES PROGRAMME II'!K36 -> 0 | H36: ='DEPENSES PROGRAMME III'!K36 -> 0 | J36: ='DEPENSES PROGRAMME I'!L36 -> 0 | K36: ='DEPENSES PROGRAMME II'!L36 -> 0 | L36: ='DEPENSES PROGRAMME III'!L36 -> 0 | N36: ='DEPENSES PROGRAMME I'!M36 -> 0 | O36: ='DEPENSES PROGRAMME II'!M36 -> 0 | P36: ='DEPENSES PROGRAMME III'!M36 -> 0
D37: 6117 | E37: Habillement | F37: ='DEPENSES PROGRAMME I'!K37 -> 0 | G37: ='DEPENSES PROGRAMME II'!K37 -> 0 | H37: ='DEPENSES PROGRAMME III'!K37 -> 0 | J37: ='DEPENSES PROGRAMME I'!L37 -> 0 | K37: ='DEPENSES PROGRAMME II'!L37 -> 0 | L37: ='DEPENSES PROGRAMME III'!L37 -> 0 | N37: ='DEPENSES PROGRAMME I'!M37 -> 0 | O37: ='DEPENSES PROGRAMME II'!M37 -> 0 | P37: ='DEPENSES PROGRAMME III'!M37 -> 0
C38: 612 | E38: Achats de biens à usage spécifique | F38: =SUM(F39:F46) -> 0 | G38: =SUM(G39:G46) -> 0 | H38: =SUM(H39:H46) -> 0 | J38: =SUM(J39:J46) -> 0 | K38: =SUM(K39:K46) -> 0 | L38: =SUM(L39:L46) -> 0 | N38: =SUM(N39:N46) -> 0 | O38: =SUM(O39:O46) -> 0 | P38: =SUM(P39:P46) -> 0
D39: 6121 | E39: Fornitures scolaires | F39: ='DEPENSES PROGRAMME I'!K39 -> 0 | G39: ='DEPENSES PROGRAMME II'!K39 -> 0 | H39: ='DEPENSES PROGRAMME III'!K39 -> 0 | J39: ='DEPENSES PROGRAMME I'!L39 -> 0 | K39: ='DEPENSES PROGRAMME II'!L39 -> 0 | L39: ='DEPENSES PROGRAMME III'!L39 -> 0 | N39: ='DEPENSES PROGRAMME I'!M39 -> 0 | O39: ='DEPENSES PROGRAMME II'!M39 -> 0 | P39: ='DEPENSES PROGRAMME III'!M39 -> 0
D40: 6122 | E40: Consommables médicaux | F40: ='DEPENSES PROGRAMME I'!K40 -> 0 | G40: ='DEPENSES PROGRAMME II'!K40 -> 0 | H40: ='DEPENSES PROGRAMME III'!K40 -> 0 | J40: ='DEPENSES PROGRAMME I'!L40 -> 0 | K40: ='DEPENSES PROGRAMME II'!L40 -> 0 | L40: ='DEPENSES PROGRAMME III'!L40 -> 0 | N40: ='DEPENSES PROGRAMME I'!M40 -> 0 | O40: ='DEPENSES PROGRAMME II'!M40 -> 0 | P40: ='DEPENSES PROGRAMME III'!M40 -> 0
D41: 6123 | E41: Produits pahrmaceutiques | F41: ='DEPENSES PROGRAMME I'!K41 -> 0 | G41: ='DEPENSES PROGRAMME II'!K41 -> 0 | H41: ='DEPENSES PROGRAMME III'!K41 -> 0 | J41: ='DEPENSES PROGRAMME I'!L41 -> 0 | K41: ='DEPENSES PROGRAMME II'!L41 -> 0 | L41: ='DEPENSES PROGRAMME III'!L41 -> 0 | N41: ='DEPENSES PROGRAMME I'!M41 -> 0 | O41: ='DEPENSES PROGRAMME II'!M41 -> 0 | P41: ='DEPENSES PROGRAMME III'!M41 -> 0
D42: 6124 | E42: Produits vétérianaires | F42: ='DEPENSES PROGRAMME I'!K42 -> 0 | G42: ='DEPENSES PROGRAMME II'!K42 -> 0 | H42: ='DEPENSES PROGRAMME III'!K42 -> 0 | J42: ='DEPENSES PROGRAMME I'!L42 -> 0 | K42: ='DEPENSES PROGRAMME II'!L42 -> 0 | L42: ='DEPENSES PROGRAMME III'!L42 -> 0 | N42: ='DEPENSES PROGRAMME I'!M42 -> 0 | O42: ='DEPENSES PROGRAMME II'!M42 -> 0 | P42: ='DEPENSES PROGRAMME III'!M42 -> 0
D43: 6125 | E43: Produits alimentaires | F43: ='DEPENSES PROGRAMME I'!K43 -> 0 | G43: ='DEPENSES PROGRAMME II'!K43 -> 0 | H43: ='DEPENSES PROGRAMME III'!K43 -> 0 | J43: ='DEPENSES PROGRAMME I'!L43 -> 0 | K43: ='DEPENSES PROGRAMME II'!L43 -> 0 | L43: ='DEPENSES PROGRAMME III'!L43 -> 0 | N43: ='DEPENSES PROGRAMME I'!M43 -> 0 | O43: ='DEPENSES PROGRAMME II'!M43 -> 0 | P43: ='DEPENSES PROGRAMME III'!M43 -> 0
D44: 6126 | E44: Intrants agricoles | F44: ='DEPENSES PROGRAMME I'!K44 -> 0 | G44: ='DEPENSES PROGRAMME II'!K44 -> 0 | H44: ='DEPENSES PROGRAMME III'!K44 -> 0 | J44: ='DEPENSES PROGRAMME I'!L44 -> 0 | K44: ='DEPENSES PROGRAMME II'!L44 -> 0 | L44: ='DEPENSES PROGRAMME III'!L44 -> 0 | N44: ='DEPENSES PROGRAMME I'!M44 -> 0 | O44: ='DEPENSES PROGRAMME II'!M44 -> 0 | P44: ='DEPENSES PROGRAMME III'!M44 -> 0
D45: 6127 | E45: Fournitures sportives | F45: ='DEPENSES PROGRAMME I'!K45 -> 0 | G45: ='DEPENSES PROGRAMME II'!K45 -> 0 | H45: ='DEPENSES PROGRAMME III'!K45 -> 0 | J45: ='DEPENSES PROGRAMME I'!L45 -> 0 | K45: ='DEPENSES PROGRAMME II'!L45 -> 0 | L45: ='DEPENSES PROGRAMME III'!L45 -> 0 | N45: ='DEPENSES PROGRAMME I'!M45 -> 0 | O45: ='DEPENSES PROGRAMME II'!M45 -> 0 | P45: ='DEPENSES PROGRAMME III'!M45 -> 0
D46: 6128 | E46: Fournitures ménagères | F46: ='DEPENSES PROGRAMME I'!K46 -> 0 | G46: ='DEPENSES PROGRAMME II'!K46 -> 0 | H46: ='DEPENSES PROGRAMME III'!K46 -> 0 | J46: ='DEPENSES PROGRAMME I'!L46 -> 0 | K46: ='DEPENSES PROGRAMME II'!L46 -> 0 | L46: ='DEPENSES PROGRAMME III'!L46 -> 0 | N46: ='DEPENSES PROGRAMME I'!M46 -> 0 | O46: ='DEPENSES PROGRAMME II'!M46 -> 0 | P46: ='DEPENSES PROGRAMME III'!M46 -> 0
C47: 613 | E47: Carburants, Lubrifiants et combustibles | F47: =SUM(F48:F50) -> 0 | G47: =SUM(G48:G50) -> 0 | H47: =SUM(H48:H50) -> 0 | J47: =SUM(J48:J50) -> 0 | K47: =SUM(K48:K50) -> 0 | L47: =SUM(L48:L50) -> 0 | N47: =SUM(N48:N50) -> 0 | O47: =SUM(O48:O50) -> 0 | P47: =SUM(P48:P50) -> 0
D48: 6131 | E48: Carburants et Lubrifiants | F48: ='DEPENSES PROGRAMME I'!K48 -> 0 | G48: ='DEPENSES PROGRAMME II'!K48 -> 0 | H48: ='DEPENSES PROGRAMME III'!K48 -> 0 | J48: ='DEPENSES PROGRAMME I'!L48 -> 0 | K48: ='DEPENSES PROGRAMME II'!L48 -> 0 | L48: ='DEPENSES PROGRAMME III'!L48 -> 0 | N48: ='DEPENSES PROGRAMME I'!M48 -> 0 | O48: ='DEPENSES PROGRAMME II'!M48 -> 0 | P48: ='DEPENSES PROGRAMME III'!M48 -> 0
D49: 6132 | E49: Gaz | F49: ='DEPENSES PROGRAMME I'!K49 -> 0 | G49: ='DEPENSES PROGRAMME II'!K49 -> 0 | H49: ='DEPENSES PROGRAMME III'!K49 -> 0 | J49: ='DEPENSES PROGRAMME I'!L49 -> 0 | K49: ='DEPENSES PROGRAMME II'!L49 -> 0 | L49: ='DEPENSES PROGRAMME III'!L49 -> 0 | N49: ='DEPENSES PROGRAMME I'!M49 -> 0 | O49: ='DEPENSES PROGRAMME II'!M49 -> 0 | P49: ='DEPENSES PROGRAMME III'!M49 -> 0
D50: 6138 | E50: Autres combustibles | F50: ='DEPENSES PROGRAMME I'!K50 -> 0 | G50: ='DEPENSES PROGRAMME II'!K50 -> 0 | H50: ='DEPENSES PROGRAMME III'!K50 -> 0 | J50: ='DEPENSES PROGRAMME I'!L50 -> 0 | K50: ='DEPENSES PROGRAMME II'!L50 -> 0 | L50: ='DEPENSES PROGRAMME III'!L50 -> 0 | N50: ='DEPENSES PROGRAMME I'!M50 -> 0 | O50: ='DEPENSES PROGRAMME II'!M50 -> 0 | P50: ='DEPENSES PROGRAMME III'!M50 -> 0
C51: 616 | E51: Variation de stocks | F51: =SUM(F52:F55) -> 0 | G51: =SUM(G52:G55) -> 0 | H51: =SUM(H52:H55) -> 0 | J51: =SUM(J52:J55) -> 0 | K51: =SUM(K52:K55) -> 0 | L51: =SUM(L52:L55) -> 0 | N51: =SUM(N52:N55) -> 0 | O51: =SUM(O52:O55) -> 0 | P51: =SUM(P52:P55) -> 0
D52: 6161 | E52: Variation des stocks de biens de fonctionnement général | F52: ='DEPENSES PROGRAMME I'!K52 -> 0 | G52: ='DEPENSES PROGRAMME II'!K52 -> 0 | H52: ='DEPENSES PROGRAMME III'!K52 -> 0 | J52: ='DEPENSES PROGRAMME I'!L52 -> 0 | K52: ='DEPENSES PROGRAMME II'!L52 -> 0 | L52: ='DEPENSES PROGRAMME III'!L52 -> 0 | N52: ='DEPENSES PROGRAMME I'!M52 -> 0 | O52: ='DEPENSES PROGRAMME II'!M52 -> 0 | P52: ='DEPENSES PROGRAMME III'!M52 -> 0
D53: 6162 | E53: Variation des stoccks de biens à usage spécifique | F53: ='DEPENSES PROGRAMME I'!K53 -> 0 | G53: ='DEPENSES PROGRAMME II'!K53 -> 0 | H53: ='DEPENSES PROGRAMME III'!K53 -> 0 | J53: ='DEPENSES PROGRAMME I'!L53 -> 0 | K53: ='DEPENSES PROGRAMME II'!L53 -> 0 | L53: ='DEPENSES PROGRAMME III'!L53 -> 0 | N53: ='DEPENSES PROGRAMME I'!M53 -> 0 | O53: ='DEPENSES PROGRAMME II'!M53 -> 0 | P53: ='DEPENSES PROGRAMME III'!M53 -> 0
D54: 6163 | E54: Variation des stocks de carburants, Lubrifiants et combustibles | F54: ='DEPENSES PROGRAMME I'!K54 -> 0 | G54: ='DEPENSES PROGRAMME II'!K54 -> 0 | H54: ='DEPENSES PROGRAMME III'!K54 -> 0 | J54: ='DEPENSES PROGRAMME I'!L54 -> 0 | K54: ='DEPENSES PROGRAMME II'!L54 -> 0 | L54: ='DEPENSES PROGRAMME III'!L54 -> 0 | N54: ='DEPENSES PROGRAMME I'!M54 -> 0 | O54: ='DEPENSES PROGRAMME II'!M54 -> 0 | P54: ='DEPENSES PROGRAMME III'!M54 -> 0
D55: 6168 | E55: Variation des staock d'autres achats | F55: ='DEPENSES PROGRAMME I'!K55 -> 0 | G55: ='DEPENSES PROGRAMME II'!K55 -> 0 | H55: ='DEPENSES PROGRAMME III'!K55 -> 0 | J55: ='DEPENSES PROGRAMME I'!L55 -> 0 | K55: ='DEPENSES PROGRAMME II'!L55 -> 0 | L55: ='DEPENSES PROGRAMME III'!L55 -> 0 | N55: ='DEPENSES PROGRAMME I'!M55 -> 0 | O55: ='DEPENSES PROGRAMME II'!M55 -> 0 | P55: ='DEPENSES PROGRAMME III'!M55 -> 0
C56: 618 | E56: Autres achats | F56: =SUM(F57:F59) -> 0 | G56: =SUM(G57:G59) -> 0 | H56: =SUM(H57:H59) -> 0 | J56: =SUM(J57:J59) -> 0 | K56: =SUM(K57:K59) -> 0 | L56: =SUM(L57:L59) -> 0 | N56: =SUM(N57:N59) -> 0 | O56: =SUM(O57:O59) -> 0 | P56: =SUM(P57:P59) -> 0
D57: 6181 | E57: Achats de matières premières | F57: ='DEPENSES PROGRAMME I'!K57 -> 0 | G57: ='DEPENSES PROGRAMME II'!K57 -> 0 | H57: ='DEPENSES PROGRAMME III'!K57 -> 0 | J57: ='DEPENSES PROGRAMME I'!L57 -> 0 | K57: ='DEPENSES PROGRAMME II'!L57 -> 0 | L57: ='DEPENSES PROGRAMME III'!L57 -> 0 | N57: ='DEPENSES PROGRAMME I'!M57 -> 0 | O57: ='DEPENSES PROGRAMME II'!M57 -> 0 | P57: ='DEPENSES PROGRAMME III'!M57 -> 0
D58: 6182 | E58: Achats de marchandises destinées à être revendues | F58: ='DEPENSES PROGRAMME I'!K58 -> 0 | G58: ='DEPENSES PROGRAMME II'!K58 -> 0 | H58: ='DEPENSES PROGRAMME III'!K58 -> 0 | J58: ='DEPENSES PROGRAMME I'!L58 -> 0 | K58: ='DEPENSES PROGRAMME II'!L58 -> 0 | L58: ='DEPENSES PROGRAMME III'!L58 -> 0 | N58: ='DEPENSES PROGRAMME I'!M58 -> 0 | O58: ='DEPENSES PROGRAMME II'!M58 -> 0 | P58: ='DEPENSES PROGRAMME III'!M58 -> 0
D59: 6183 | E59: Emballages | F59: ='DEPENSES PROGRAMME I'!K59 -> 0 | G59: ='DEPENSES PROGRAMME II'!K59 -> 0 | H59: ='DEPENSES PROGRAMME III'!K59 -> 0 | J59: ='DEPENSES PROGRAMME I'!L59 -> 0 | K59: ='DEPENSES PROGRAMME II'!L59 -> 0 | L59: ='DEPENSES PROGRAMME III'!L59 -> 0 | N59: ='DEPENSES PROGRAMME I'!M59 -> 0 | O59: ='DEPENSES PROGRAMME II'!M59 -> 0 | P59: ='DEPENSES PROGRAMME III'!M59 -> 0
B60: 62 | E60: ACHATS DE SERVICES ET CHARGES PERMANENTES | F60: =SUM(F61,F70,F77,F83,F87,F89,F96,F103) -> 0 | G60: =SUM(G61,G70,G77,G83,G87,G89,G96,G103) -> 0 | H60: =SUM(H61,H70,H77,H83,H87,H89,H96,H103) -> 0 | I60: =SUM(F60,G60,H60) -> 0 | J60: =SUM(J61,J70,J77,J83,J87,J89,J96,J103) -> 0 | K60: =SUM(K61,K70,K77,K83,K87,K89,K96,K103) -> 0 | L60: =SUM(L61,L70,L77,L83,L87,L89,L96,L103) -> 0 | M60: =SUM(J60,K60,L60) -> 0 | N60: =SUM(N61,N70,N77,N83,N87,N89,N96,N103) -> 0 | O60: =SUM(O61,O70,O77,O83,O87,O89,O96,O103) -> 0 | P60: =SUM(P61,P70,P77,P83,P87,P89,P96,P103) -> 0 | Q60: =SUM(N60,O60,P60) -> 0
C61: 621 | E61: Entretien et maintenance | F61: =SUM(F62:F69) -> 0 | G61: =SUM(G62:G69) -> 0 | H61: =SUM(H62:H69) -> 0 | J61: =SUM(J62:J69) -> 0 | K61: =SUM(K62:K69) -> 0 | L61: =SUM(L62:L69) -> 0 | N61: =SUM(N62:N69) -> 0 | O61: =SUM(O62:O69) -> 0 | P61: =SUM(P62:P69) -> 0
D62: 6211 | E62: Entretien de bâtiments | F62: ='DEPENSES PROGRAMME I'!K62 -> 0 | G62: ='DEPENSES PROGRAMME II'!K62 -> 0 | H62: ='DEPENSES PROGRAMME III'!K62 -> 0 | J62: ='DEPENSES PROGRAMME I'!L62 -> 0 | K62: ='DEPENSES PROGRAMME II'!L62 -> 0 | L62: ='DEPENSES PROGRAMME III'!L62 -> 0 | N62: ='DEPENSES PROGRAMME I'!M62 -> 0 | O62: ='DEPENSES PROGRAMME II'!M62 -> 0 | P62: ='DEPENSES PROGRAMME III'!M62 -> 0
D63: 6212 | E63: Entretien des autres infrastructures | F63: ='DEPENSES PROGRAMME I'!K63 -> 0 | G63: ='DEPENSES PROGRAMME II'!K63 -> 0 | H63: ='DEPENSES PROGRAMME III'!K63 -> 0 | J63: ='DEPENSES PROGRAMME I'!L63 -> 0 | K63: ='DEPENSES PROGRAMME II'!L63 -> 0 | L63: ='DEPENSES PROGRAMME III'!L63 -> 0 | N63: ='DEPENSES PROGRAMME I'!M63 -> 0 | O63: ='DEPENSES PROGRAMME II'!M63 -> 0 | P63: ='DEPENSES PROGRAMME III'!M63 -> 0
D64: 6213 | E64: Entretien de véhicules | F64: ='DEPENSES PROGRAMME I'!K64 -> 0 | G64: ='DEPENSES PROGRAMME II'!K64 -> 0 | H64: ='DEPENSES PROGRAMME III'!K64 -> 0 | J64: ='DEPENSES PROGRAMME I'!L64 -> 0 | K64: ='DEPENSES PROGRAMME II'!L64 -> 0 | L64: ='DEPENSES PROGRAMME III'!L64 -> 0 | N64: ='DEPENSES PROGRAMME I'!M64 -> 0 | O64: ='DEPENSES PROGRAMME II'!M64 -> 0 | P64: ='DEPENSES PROGRAMME III'!M64 -> 0
D65: 6214 | E65: Entretien de matériels techniques | F65: ='DEPENSES PROGRAMME I'!K65 -> 0 | G65: ='DEPENSES PROGRAMME II'!K65 -> 0 | H65: ='DEPENSES PROGRAMME III'!K65 -> 0 | J65: ='DEPENSES PROGRAMME I'!L65 -> 0 | K65: ='DEPENSES PROGRAMME II'!L65 -> 0 | L65: ='DEPENSES PROGRAMME III'!L65 -> 0 | N65: ='DEPENSES PROGRAMME I'!M65 -> 0 | O65: ='DEPENSES PROGRAMME II'!M65 -> 0 | P65: ='DEPENSES PROGRAMME III'!M65 -> 0
D66: 6215 | E66: Entretien et réparation des matériels et mobiliers de bureau | F66: ='DEPENSES PROGRAMME I'!K66 -> 0 | G66: ='DEPENSES PROGRAMME II'!K66 -> 0 | H66: ='DEPENSES PROGRAMME III'!K66 -> 0 | J66: ='DEPENSES PROGRAMME I'!L66 -> 0 | K66: ='DEPENSES PROGRAMME II'!L66 -> 0 | L66: ='DEPENSES PROGRAMME III'!L66 -> 0 | N66: ='DEPENSES PROGRAMME I'!M66 -> 0 | O66: ='DEPENSES PROGRAMME II'!M66 -> 0 | P66: ='DEPENSES PROGRAMME III'!M66 -> 0
D67: 6216 | E67: Entretien et réparation des matériels et mobiliers de logement | F67: ='DEPENSES PROGRAMME I'!K67 -> 0 | G67: ='DEPENSES PROGRAMME II'!K67 -> 0 | H67: ='DEPENSES PROGRAMME III'!K67 -> 0 | J67: ='DEPENSES PROGRAMME I'!L67 -> 0 | K67: ='DEPENSES PROGRAMME II'!L67 -> 0 | L67: ='DEPENSES PROGRAMME III'!L67 -> 0 | N67: ='DEPENSES PROGRAMME I'!M67 -> 0 | O67: ='DEPENSES PROGRAMME II'!M67 -> 0 | P67: ='DEPENSES PROGRAMME III'!M67 -> 0
D68: 6217 | E68: Entretien et réparation des matériels et mobiliers scolaires | F68: ='DEPENSES PROGRAMME I'!K68 -> 0 | G68: ='DEPENSES PROGRAMME II'!K68 -> 0 | H68: ='DEPENSES PROGRAMME III'!K68 -> 0 | J68: ='DEPENSES PROGRAMME I'!L68 -> 0 | K68: ='DEPENSES PROGRAMME II'!L68 -> 0 | L68: ='DEPENSES PROGRAMME III'!L68 -> 0 | N68: ='DEPENSES PROGRAMME I'!M68 -> 0 | O68: ='DEPENSES PROGRAMME II'!M68 -> 0 | P68: ='DEPENSES PROGRAMME III'!M68 -> 0
D69: 6218 | E69: Maintenance du matériel informatique | F69: ='DEPENSES PROGRAMME I'!K69 -> 0 | G69: ='DEPENSES PROGRAMME II'!K69 -> 0 | H69: ='DEPENSES PROGRAMME III'!K69 -> 0 | J69: ='DEPENSES PROGRAMME I'!L69 -> 0 | K69: ='DEPENSES PROGRAMME II'!L69 -> 0 | L69: ='DEPENSES PROGRAMME III'!L69 -> 0 | N69: ='DEPENSES PROGRAMME I'!M69 -> 0 | O69: ='DEPENSES PROGRAMME II'!M69 -> 0 | P69: ='DEPENSES PROGRAMME III'!M69 -> 0
C70: 622 | E70: Charges de représentation, d'information, de documentation et d'encadrement | F70: =SUM(F71:F76) -> 0 | G70: =SUM(G71:G76) -> 0 | H70: =SUM(H71:H76) -> 0 | J70: =SUM(J71:J76) -> 0 | K70: =SUM(K71:K76) -> 0 | L70: =SUM(L71:L76) -> 0 | N70: =SUM(N71:N76) -> 0 | O70: =SUM(O71:O76) -> 0 | P70: =SUM(P71:P76) -> 0
D71: 6221 | E71: Fêtes et cérémonies officielles | F71: ='DEPENSES PROGRAMME I'!K71 -> 0 | G71: ='DEPENSES PROGRAMME II'!K71 -> 0 | H71: ='DEPENSES PROGRAMME III'!K71 -> 0 | J71: ='DEPENSES PROGRAMME I'!L71 -> 0 | K71: ='DEPENSES PROGRAMME II'!L71 -> 0 | L71: ='DEPENSES PROGRAMME III'!L71 -> 0 | N71: ='DEPENSES PROGRAMME I'!M71 -> 0 | O71: ='DEPENSES PROGRAMME II'!M71 -> 0 | P71: ='DEPENSES PROGRAMME III'!M71 -> 0
D72: 6222 | E72: Charges de représentation : visites officielles | F72: ='DEPENSES PROGRAMME I'!K72 -> 0 | G72: ='DEPENSES PROGRAMME II'!K72 -> 0 | H72: ='DEPENSES PROGRAMME III'!K72 -> 0 | J72: ='DEPENSES PROGRAMME I'!L72 -> 0 | K72: ='DEPENSES PROGRAMME II'!L72 -> 0 | L72: ='DEPENSES PROGRAMME III'!L72 -> 0 | N72: ='DEPENSES PROGRAMME I'!M72 -> 0 | O72: ='DEPENSES PROGRAMME II'!M72 -> 0 | P72: ='DEPENSES PROGRAMME III'!M72 -> 0
D73: 6223 | E73: Docuementation et abonnement | F73: ='DEPENSES PROGRAMME I'!K73 -> 0 | G73: ='DEPENSES PROGRAMME II'!K73 -> 0 | H73: ='DEPENSES PROGRAMME III'!K73 -> 0 | J73: ='DEPENSES PROGRAMME I'!L73 -> 0 | K73: ='DEPENSES PROGRAMME II'!L73 -> 0 | L73: ='DEPENSES PROGRAMME III'!L73 -> 0 | N73: ='DEPENSES PROGRAMME I'!M73 -> 0 | O73: ='DEPENSES PROGRAMME II'!M73 -> 0 | P73: ='DEPENSES PROGRAMME III'!M73 -> 0
D74: 6224 | E74: Impression, reliures, insertions, publicité et promotion | F74: ='DEPENSES PROGRAMME I'!K74 -> 0 | G74: ='DEPENSES PROGRAMME II'!K74 -> 0 | H74: ='DEPENSES PROGRAMME III'!K74 -> 0 | J74: ='DEPENSES PROGRAMME I'!L74 -> 0 | K74: ='DEPENSES PROGRAMME II'!L74 -> 0 | L74: ='DEPENSES PROGRAMME III'!L74 -> 0 | N74: ='DEPENSES PROGRAMME I'!M74 -> 0 | O74: ='DEPENSES PROGRAMME II'!M74 -> 0 | P74: ='DEPENSES PROGRAMME III'!M74 -> 0
D75: 6225 | E75: Frais de Colloques, séminaires, conférences | F75: ='DEPENSES PROGRAMME I'!K75 -> 0 | G75: ='DEPENSES PROGRAMME II'!K75 -> 0 | H75: ='DEPENSES PROGRAMME III'!K75 -> 0 | J75: ='DEPENSES PROGRAMME I'!L75 -> 0 | K75: ='DEPENSES PROGRAMME II'!L75 -> 0 | L75: ='DEPENSES PROGRAMME III'!L75 -> 0 | N75: ='DEPENSES PROGRAMME I'!M75 -> 0 | O75: ='DEPENSES PROGRAMME II'!M75 -> 0 | P75: ='DEPENSES PROGRAMME III'!M75 -> 0
D76: 6226 | E76: Foires, exposition | F76: ='DEPENSES PROGRAMME I'!K76 -> 0 | G76: ='DEPENSES PROGRAMME II'!K76 -> 0 | H76: ='DEPENSES PROGRAMME III'!K76 -> 0 | J76: ='DEPENSES PROGRAMME I'!L76 -> 0 | K76: ='DEPENSES PROGRAMME II'!L76 -> 0 | L76: ='DEPENSES PROGRAMME III'!L76 -> 0 | N76: ='DEPENSES PROGRAMME I'!M76 -> 0 | O76: ='DEPENSES PROGRAMME II'!M76 -> 0 | P76: ='DEPENSES PROGRAMME III'!M76 -> 0
C77: 623 | E77: Charges de transport | F77: =SUM(F78:F82) -> 0 | G77: =SUM(G78:G82) -> 0 | H77: =SUM(H78:H82) -> 0 | J77: =SUM(J78:J82) -> 0 | K77: =SUM(K78:K82) -> 0 | L77: =SUM(L78:L82) -> 0 | N77: =SUM(N78:N82) -> 0 | O77: =SUM(O78:O82) -> 0 | P77: =SUM(P78:P82) -> 0
D78: 6231 | E78: Frais de déplacement intérieur | F78: ='DEPENSES PROGRAMME I'!K78 -> 0 | G78: ='DEPENSES PROGRAMME II'!K78 -> 0 | H78: ='DEPENSES PROGRAMME III'!K78 -> 0 | J78: ='DEPENSES PROGRAMME I'!L78 -> 0 | K78: ='DEPENSES PROGRAMME II'!L78 -> 0 | L78: ='DEPENSES PROGRAMME III'!L78 -> 0 | N78: ='DEPENSES PROGRAMME I'!M78 -> 0 | O78: ='DEPENSES PROGRAMME II'!M78 -> 0 | P78: ='DEPENSES PROGRAMME III'!M78 -> 0
D79: 6232 | E79: Frais de déplacement extérieur | F79: ='DEPENSES PROGRAMME I'!K79 -> 0 | G79: ='DEPENSES PROGRAMME II'!K79 -> 0 | H79: ='DEPENSES PROGRAMME III'!K79 -> 0 | J79: ='DEPENSES PROGRAMME I'!L79 -> 0 | K79: ='DEPENSES PROGRAMME II'!L79 -> 0 | L79: ='DEPENSES PROGRAMME III'!L79 -> 0 | N79: ='DEPENSES PROGRAMME I'!M79 -> 0 | O79: ='DEPENSES PROGRAMME II'!M79 -> 0 | P79: ='DEPENSES PROGRAMME III'!M79 -> 0
D80: 6233 | E80: Locations de voitures | F80: ='DEPENSES PROGRAMME I'!K80 -> 0 | G80: ='DEPENSES PROGRAMME II'!K80 -> 0 | H80: ='DEPENSES PROGRAMME III'!K80 -> 0 | J80: ='DEPENSES PROGRAMME I'!L80 -> 0 | K80: ='DEPENSES PROGRAMME II'!L80 -> 0 | L80: ='DEPENSES PROGRAMME III'!L80 -> 0 | N80: ='DEPENSES PROGRAMME I'!M80 -> 0 | O80: ='DEPENSES PROGRAMME II'!M80 -> 0 | P80: ='DEPENSES PROGRAMME III'!M80 -> 0
D81: 6234 | E81: Transport administratif | F81: ='DEPENSES PROGRAMME I'!K81 -> 0 | G81: ='DEPENSES PROGRAMME II'!K81 -> 0 | H81: ='DEPENSES PROGRAMME III'!K81 -> 0 | J81: ='DEPENSES PROGRAMME I'!L81 -> 0 | K81: ='DEPENSES PROGRAMME II'!L81 -> 0 | L81: ='DEPENSES PROGRAMME III'!L81 -> 0 | N81: ='DEPENSES PROGRAMME I'!M81 -> 0 | O81: ='DEPENSES PROGRAMME II'!M81 -> 0 | P81: ='DEPENSES PROGRAMME III'!M81 -> 0
D82: 6235 | E82: Transport de bien | F82: ='DEPENSES PROGRAMME I'!K82 -> 0 | G82: ='DEPENSES PROGRAMME II'!K82 -> 0 | H82: ='DEPENSES PROGRAMME III'!K82 -> 0 | J82: ='DEPENSES PROGRAMME I'!L82 -> 0 | K82: ='DEPENSES PROGRAMME II'!L82 -> 0 | L82: ='DEPENSES PROGRAMME III'!L82 -> 0 | N82: ='DEPENSES PROGRAMME I'!M82 -> 0 | O82: ='DEPENSES PROGRAMME II'!M82 -> 0 | P82: ='DEPENSES PROGRAMME III'!M82 -> 0
C83: 624 | E83: Indemnités de mission | F83: =SUM(F84:F86) -> 0 | G83: =SUM(G84:G86) -> 0 | H83: =SUM(H84:H86) -> 0 | J83: =SUM(J84:J86) -> 0 | K83: =SUM(K84:K86) -> 0 | L83: =SUM(L84:L86) -> 0 | N83: =SUM(N84:N86) -> 0 | O83: =SUM(O84:O86) -> 0 | P83: =SUM(P84:P86) -> 0
D84: 6241 | E84: Indemnité de mission intérieure | F84: ='DEPENSES PROGRAMME I'!K84 -> 0 | G84: ='DEPENSES PROGRAMME II'!K84 -> 0 | H84: ='DEPENSES PROGRAMME III'!K84 -> 0 | J84: ='DEPENSES PROGRAMME I'!L84 -> 0 | K84: ='DEPENSES PROGRAMME II'!L84 -> 0 | L84: ='DEPENSES PROGRAMME III'!L84 -> 0 | N84: ='DEPENSES PROGRAMME I'!M84 -> 0 | O84: ='DEPENSES PROGRAMME II'!M84 -> 0 | P84: ='DEPENSES PROGRAMME III'!M84 -> 0
D85: 6242 | E85: Indemnité de mission extérieure | F85: ='DEPENSES PROGRAMME I'!K85 -> 0 | G85: ='DEPENSES PROGRAMME II'!K85 -> 0 | H85: ='DEPENSES PROGRAMME III'!K85 -> 0 | J85: ='DEPENSES PROGRAMME I'!L85 -> 0 | K85: ='DEPENSES PROGRAMME II'!L85 -> 0 | L85: ='DEPENSES PROGRAMME III'!L85 -> 0 | N85: ='DEPENSES PROGRAMME I'!M85 -> 0 | O85: ='DEPENSES PROGRAMME II'!M85 -> 0 | P85: ='DEPENSES PROGRAMME III'!M85 -> 0
D86: 6243 | E86: Viatique | F86: ='DEPENSES PROGRAMME I'!K86 -> 0 | G86: ='DEPENSES PROGRAMME II'!K86 -> 0 | H86: ='DEPENSES PROGRAMME III'!K86 -> 0 | J86: ='DEPENSES PROGRAMME I'!L86 -> 0 | K86: ='DEPENSES PROGRAMME II'!L86 -> 0 | L86: ='DEPENSES PROGRAMME III'!L86 -> 0 | N86: ='DEPENSES PROGRAMME I'!M86 -> 0 | O86: ='DEPENSES PROGRAMME II'!M86 -> 0 | P86: ='DEPENSES PROGRAMME III'!M86 -> 0
C87: 625 | E87: Eau et éléctricité | F87: =SUM(F88) -> 0 | G87: =SUM(G88) -> 0 | H87: =SUM(H88) -> 0 | J87: =SUM(J88) -> 0 | K87: =SUM(K88) -> 0 | L87: =SUM(L88) -> 0 | N87: =SUM(N88) -> 0 | O87: =SUM(O88) -> 0 | P87: =SUM(P88) -> 0
D88: 6250 | E88: Eau et électricité | F88: ='DEPENSES PROGRAMME I'!K88 -> 0 | G88: ='DEPENSES PROGRAMME II'!K88 -> 0 | H88: ='DEPENSES PROGRAMME III'!K88 -> 0 | J88: ='DEPENSES PROGRAMME I'!L88 -> 0 | K88: ='DEPENSES PROGRAMME II'!L88 -> 0 | L88: ='DEPENSES PROGRAMME III'!L88 -> 0 | N88: ='DEPENSES PROGRAMME I'!M88 -> 0 | O88: ='DEPENSES PROGRAMME II'!M88 -> 0 | P88: ='DEPENSES PROGRAMME III'!M88 -> 0
C89: 626 | E89: Poste et télécommunications | F89: =SUM(F90:F95) -> 0 | G89: =SUM(G90:G95) -> 0 | H89: =SUM(H90:H95) -> 0 | J89: =SUM(J90:J95) -> 0 | K89: =SUM(K90:K95) -> 0 | L89: =SUM(L90:L95) -> 0 | N89: =SUM(N90:N95) -> 0 | O89: =SUM(O90:O95) -> 0 | P89: =SUM(P90:P95) -> 0
D90: 6261 | E90: Frais postaux | F90: ='DEPENSES PROGRAMME I'!K90 -> 0 | G90: ='DEPENSES PROGRAMME II'!K90 -> 0 | H90: ='DEPENSES PROGRAMME III'!K90 -> 0 | J90: ='DEPENSES PROGRAMME I'!L90 -> 0 | K90: ='DEPENSES PROGRAMME II'!L90 -> 0 | L90: ='DEPENSES PROGRAMME III'!L90 -> 0 | N90: ='DEPENSES PROGRAMME I'!M90 -> 0 | O90: ='DEPENSES PROGRAMME II'!M90 -> 0 | P90: ='DEPENSES PROGRAMME III'!M90 -> 0
D91: 6262 | E91: Redevances téléphoniques | F91: ='DEPENSES PROGRAMME I'!K91 -> 0 | G91: ='DEPENSES PROGRAMME II'!K91 -> 0 | H91: ='DEPENSES PROGRAMME III'!K91 -> 0 | J91: ='DEPENSES PROGRAMME I'!L91 -> 0 | K91: ='DEPENSES PROGRAMME II'!L91 -> 0 | L91: ='DEPENSES PROGRAMME III'!L91 -> 0 | N91: ='DEPENSES PROGRAMME I'!M91 -> 0 | O91: ='DEPENSES PROGRAMME II'!M91 -> 0 | P91: ='DEPENSES PROGRAMME III'!M91 -> 0
D92: 6263 | E92: Redevances téléphoniques mobiles | F92: ='DEPENSES PROGRAMME I'!K92 -> 0 | G92: ='DEPENSES PROGRAMME II'!K92 -> 0 | H92: ='DEPENSES PROGRAMME III'!K92 -> 0 | J92: ='DEPENSES PROGRAMME I'!L92 -> 0 | K92: ='DEPENSES PROGRAMME II'!L92 -> 0 | L92: ='DEPENSES PROGRAMME III'!L92 -> 0 | N92: ='DEPENSES PROGRAMME I'!M92 -> 0 | O92: ='DEPENSES PROGRAMME II'!M92 -> 0 | P92: ='DEPENSES PROGRAMME III'!M92 -> 0
D93: 6264 | E93: Internet | F93: ='DEPENSES PROGRAMME I'!K93 -> 0 | G93: ='DEPENSES PROGRAMME II'!K93 -> 0 | H93: ='DEPENSES PROGRAMME III'!K93 -> 0 | J93: ='DEPENSES PROGRAMME I'!L93 -> 0 | K93: ='DEPENSES PROGRAMME II'!L93 -> 0 | L93: ='DEPENSES PROGRAMME III'!L93 -> 0 | N93: ='DEPENSES PROGRAMME I'!M93 -> 0 | O93: ='DEPENSES PROGRAMME II'!M93 -> 0 | P93: ='DEPENSES PROGRAMME III'!M93 -> 0
D94: 6265 | E94: Télex | F94: ='DEPENSES PROGRAMME I'!K94 -> 0 | G94: ='DEPENSES PROGRAMME II'!K94 -> 0 | H94: ='DEPENSES PROGRAMME III'!K94 -> 0 | J94: ='DEPENSES PROGRAMME I'!L94 -> 0 | K94: ='DEPENSES PROGRAMME II'!L94 -> 0 | L94: ='DEPENSES PROGRAMME III'!L94 -> 0 | N94: ='DEPENSES PROGRAMME I'!M94 -> 0 | O94: ='DEPENSES PROGRAMME II'!M94 -> 0 | P94: ='DEPENSES PROGRAMME III'!M94 -> 0
D95: 6268 | E95: Autres | F95: ='DEPENSES PROGRAMME I'!K95 -> 0 | G95: ='DEPENSES PROGRAMME II'!K95 -> 0 | H95: ='DEPENSES PROGRAMME III'!K95 -> 0 | J95: ='DEPENSES PROGRAMME I'!L95 -> 0 | K95: ='DEPENSES PROGRAMME II'!L95 -> 0 | L95: ='DEPENSES PROGRAMME III'!L95 -> 0 | N95: ='DEPENSES PROGRAMME I'!M95 -> 0 | O95: ='DEPENSES PROGRAMME II'!M95 -> 0 | P95: ='DEPENSES PROGRAMME III'!M95 -> 0
C96: 627 | E96: Charges locatives | F96: =SUM(F97:F102) -> 0 | G96: =SUM(G97:G102) -> 0 | H96: =SUM(H97:H102) -> 0 | J96: =SUM(J97:J102) -> 0 | K96: =SUM(K97:K102) -> 0 | L96: =SUM(L97:L102) -> 0 | N96: =SUM(N97:N102) -> 0 | O96: =SUM(O97:O102) -> 0 | P96: =SUM(P97:P102) -> 0
D97: 6271 | E97: Location d'immeuble de bureau | F97: ='DEPENSES PROGRAMME I'!K97 -> 0 | G97: ='DEPENSES PROGRAMME II'!K97 -> 0 | H97: ='DEPENSES PROGRAMME III'!K97 -> 0 | J97: ='DEPENSES PROGRAMME I'!L97 -> 0 | K97: ='DEPENSES PROGRAMME II'!L97 -> 0 | L97: ='DEPENSES PROGRAMME III'!L97 -> 0 | N97: ='DEPENSES PROGRAMME I'!M97 -> 0 | O97: ='DEPENSES PROGRAMME II'!M97 -> 0 | P97: ='DEPENSES PROGRAMME III'!M97 -> 0
D98: 6272 | E98: Location d'immeuble de logement | F98: ='DEPENSES PROGRAMME I'!K98 -> 0 | G98: ='DEPENSES PROGRAMME II'!K98 -> 0 | H98: ='DEPENSES PROGRAMME III'!K98 -> 0 | J98: ='DEPENSES PROGRAMME I'!L98 -> 0 | K98: ='DEPENSES PROGRAMME II'!L98 -> 0 | L98: ='DEPENSES PROGRAMME III'!L98 -> 0 | N98: ='DEPENSES PROGRAMME I'!M98 -> 0 | O98: ='DEPENSES PROGRAMME II'!M98 -> 0 | P98: ='DEPENSES PROGRAMME III'!M98 -> 0
D99: 6273 | E99: Location d'immeuble de bureau-loggement | F99: ='DEPENSES PROGRAMME I'!K99 -> 0 | G99: ='DEPENSES PROGRAMME II'!K99 -> 0 | H99: ='DEPENSES PROGRAMME III'!K99 -> 0 | J99: ='DEPENSES PROGRAMME I'!L99 -> 0 | K99: ='DEPENSES PROGRAMME II'!L99 -> 0 | L99: ='DEPENSES PROGRAMME III'!L99 -> 0 | N99: ='DEPENSES PROGRAMME I'!M99 -> 0 | O99: ='DEPENSES PROGRAMME II'!M99 -> 0 | P99: ='DEPENSES PROGRAMME III'!M99 -> 0
D100: 6274 | E100: Location de terrain | F100: ='DEPENSES PROGRAMME I'!K100 -> 0 | G100: ='DEPENSES PROGRAMME II'!K100 -> 0 | H100: ='DEPENSES PROGRAMME III'!K100 -> 0 | J100: ='DEPENSES PROGRAMME I'!L100 -> 0 | K100: ='DEPENSES PROGRAMME II'!L100 -> 0 | L100: ='DEPENSES PROGRAMME III'!L100 -> 0 | N100: ='DEPENSES PROGRAMME I'!M100 -> 0 | O100: ='DEPENSES PROGRAMME II'!M100 -> 0 | P100: ='DEPENSES PROGRAMME III'!M100 -> 0
D101: 6275 | E101: Location de matériels | F101: ='DEPENSES PROGRAMME I'!K101 -> 0 | G101: ='DEPENSES PROGRAMME II'!K101 -> 0 | H101: ='DEPENSES PROGRAMME III'!K101 -> 0 | J101: ='DEPENSES PROGRAMME I'!L101 -> 0 | K101: ='DEPENSES PROGRAMME II'!L101 -> 0 | L101: ='DEPENSES PROGRAMME III'!L101 -> 0 | N101: ='DEPENSES PROGRAMME I'!M101 -> 0 | O101: ='DEPENSES PROGRAMME II'!M101 -> 0 | P101: ='DEPENSES PROGRAMME III'!M101 -> 0
D102: 6278 | E102: Autres charges locatives | F102: ='DEPENSES PROGRAMME I'!K102 -> 0 | G102: ='DEPENSES PROGRAMME II'!K102 -> 0 | H102: ='DEPENSES PROGRAMME III'!K102 -> 0 | J102: ='DEPENSES PROGRAMME I'!L102 -> 0 | K102: ='DEPENSES PROGRAMME II'!L102 -> 0 | L102: ='DEPENSES PROGRAMME III'!L102 -> 0 | N102: ='DEPENSES PROGRAMME I'!M102 -> 0 | O102: ='DEPENSES PROGRAMME II'!M102 -> 0 | P102: ='DEPENSES PROGRAMME III'!M102 -> 0
C103: 628 | E103: Services divers | F103: =SUM(F104:F111) -> 0 | G103: =SUM(G104:G111) -> 0 | H103: =SUM(H104:H111) -> 0 | J103: =SUM(J104:J111) -> 0 | K103: =SUM(K104:K111) -> 0 | L103: =SUM(L104:L111) -> 0 | N103: =SUM(N104:N111) -> 0 | O103: =SUM(O104:O111) -> 0 | P103: =SUM(P104:P111) -> 0
D104: 6281 | E104: Rémunérations d'intermédiaires et honoraires | F104: ='DEPENSES PROGRAMME I'!K104 -> 0 | G104: ='DEPENSES PROGRAMME II'!K104 -> 0 | H104: ='DEPENSES PROGRAMME III'!K104 -> 0 | J104: ='DEPENSES PROGRAMME I'!L104 -> 0 | K104: ='DEPENSES PROGRAMME II'!L104 -> 0 | L104: ='DEPENSES PROGRAMME III'!L104 -> 0 | N104: ='DEPENSES PROGRAMME I'!M104 -> 0 | O104: ='DEPENSES PROGRAMME II'!M104 -> 0 | P104: ='DEPENSES PROGRAMME III'!M104 -> 0
...

Sheet RECAPITULATIF DEPENSES
B2: TABLEAU RECAPITULATIF DES DEPENSES
E4: COLLECTIVITE : …..........
B6: DEPENSES DE FONCTIONNEMENT
B7: COMPTE | E7: INTITULES | F7: MANDAT ADMIS | G7: PAIEMENT | H7: RESTE A PAYER
B8: 60 | E8: CHARGES DE PERSONNEL | F8: ='RECAP DEPENSES PAR PROGRAMME'!I10 -> 0 | G8: ='RECAP DEPENSES PAR PROGRAMME'!M10 -> 0 | H8: ='RECAP DEPENSES PAR PROGRAMME'!Q10 -> 0
B9: 61 | E9: ACHATS DE BIENS | F9: ='RECAP DEPENSES PAR PROGRAMME'!I29 -> 0 | G9: ='RECAP DEPENSES PAR PROGRAMME'!M29 -> 0 | H9: ='RECAP DEPENSES PAR PROGRAMME'!Q29 -> 0
B10: 62 | E10: ACHATS DE SERVICES ET CHARGES PERMANENTES | F10: ='RECAP DEPENSES PAR PROGRAMME'!I60 -> 0 | G10: ='RECAP DEPENSES PAR PROGRAMME'!M60 -> 0 | H10: ='RECAP DEPENSES PAR PROGRAMME'!Q60 -> 0
B11: 63 | E11: DEPENSES D'INTERVENTION | F11: ='RECAP DEPENSES PAR PROGRAMME'!I112 -> 0 | G11: ='RECAP DEPENSES PAR PROGRAMME'!M112 -> 0 | H11: ='RECAP DEPENSES PAR PROGRAMME'!Q112 -> 0
B12: 64 | E12: IMPOTS ET TAXES | F12: ='RECAP DEPENSES PAR PROGRAMME'!I121 -> 0 | G12: ='RECAP DEPENSES PAR PROGRAMME'!M121 -> 0 | H12: ='RECAP DEPENSES PAR PROGRAMME'!Q121 -> 0
B13: 65 | E13: TRANSFERTS ET SUBVENTIONS | F13: ='RECAP DEPENSES PAR PROGRAMME'!I132 -> 0 | G13: ='RECAP DEPENSES PAR PROGRAMME'!M132 -> 0 | H13: ='RECAP DEPENSES PAR PROGRAMME'!Q132 -> 0
B14: 66 | E14: CHARGES FINANCIERES | F14: ='RECAP DEPENSES PAR PROGRAMME'!I150 -> 0 | G14: ='RECAP DEPENSES PAR PROGRAMME'!M150 -> 0 | H14: ='RECAP DEPENSES PAR PROGRAMME'!Q150 -> 0
B15: 67 | E15: CHARGES DIVERSES | F15: ='RECAP DEPENSES PAR PROGRAMME'!I165 -> 0 | G15: ='RECAP DEPENSES PAR PROGRAMME'!M165 -> 0 | H15: ='RECAP DEPENSES PAR PROGRAMME'!Q165 -> 0
E16: TOTAL DEPENSES REELLES DE FONCTIONNEMENT | F16: =F8+F9+F10+F11+F12+F13+F14+F15 -> 0 | G16: =G8+G9+G10+G11+G12+G13+G14+G15 -> 0 | H16: =H8+H9+H10+H11+H12+H13+H14+H15 -> 0
B17: 12 | E17: EXCEDENT DE FONCTIONNEMENT | F17: ='RECAP DEPENSES PAR PROGRAMME'!I188 -> 0 | G17: ='RECAP DEPENSES PAR PROGRAMME'!M188 -> 0 | H17: ='RECAP DEPENSES PAR PROGRAMME'!Q188 -> 0
E18: TOTAL DEPENSES D'ORDRE DE FONCTIONNEMENT | F18: =SUM(F17) -> 0 | G18: =SUM(G17) -> 0 | H18: =SUM(H17) -> 0
E19: SOUS-TOTAL FONCTIONNEMENT | F19: =F16+F18 -> 0 | G19: =G16+G18 -> 0 | H19: =H16+H18 -> 0
B21: DEPENSES D'INVESTISSEMENT
B22: COMPTE | E22: INTITULES | F22: MANDAT ADMIS | G22: PAIEMENT | H22: RESTE A PAYER
B23: 16 | E23: EMPRUNTS ET DETTES ASSIMILEES | F23: ='RECAP DEPENSES PAR PROGRAMME'!I195 -> 0 | G23: ='RECAP DEPENSES PAR PROGRAMME'!M195 -> 0 | H23: ='RECAP DEPENSES PAR PROGRAMME'!Q195 -> 0
B24: 20 | E24: IMMOBILISATION INCORPORELLES | F24: ='RECAP DEPENSES PAR PROGRAMME'!I209 -> 0 | G24: ='RECAP DEPENSES PAR PROGRAMME'!M209 -> 0 | H24: ='RECAP DEPENSES PAR PROGRAMME'!Q209 -> 0
B25: 21 | E25: IMMOBILISATION CORPORELLES | F25: ='RECAP DEPENSES PAR PROGRAMME'!I224 -> 0 | G25: ='RECAP DEPENSES PAR PROGRAMME'!M224 -> 0 | H25: ='RECAP DEPENSES PAR PROGRAMME'!Q224 -> 0
E26: TOTAL DEPENSES REELLES D'INVESTISSEMENT | F26: =F23+F24+F25 -> 0 | G26: =G23+G24+G25 -> 0 | H26: =H23+H24+H25 -> 0
B27: 20 | E27: IMMOBILISATION INCORPORELLES | F27: ='RECAP DEPENSES PAR PROGRAMME'!I287 -> 0 | G27: ='RECAP DEPENSES PAR PROGRAMME'!M287 -> 0 | H27: ='RECAP DEPENSES PAR PROGRAMME'!Q287 -> 0
B28: 21 | E28: IMMOBILISATION CORPORELLES | F28: ='RECAP DEPENSES PAR PROGRAMME'!I288 -> 0 | G28: ='RECAP DEPENSES PAR PROGRAMME'!M288 -> 0 | H28: ='RECAP DEPENSES PAR PROGRAMME'!Q288 -> 0
E29: TOTAL DEPENSES D'ORDRE D'INVESTISSEMENT | F29: =SUM(F27:F28) -> 0 | G29: =SUM(G27:G28) -> 0 | H29: =SUM(H27:H28) -> 0
E30: SOUS-TOTAL INVESTISSEMENT | F30: =F26+F29 -> 0 | G30: =G26+G29 -> 0 | H30: =H26+H29 -> 0

Sheet EQUILIBRE
B2: TABLEAU D'EQUILIBRE DU COMPTE ADMINISTRATIF
C4: COLLECTIVITE : …..........
C6: DEPENSES | H6: RECETTES
B7: COMPTE | C7: INTITULES | D7: MANDAT ADMIS | E7: PAIEMENT | F7: RESTE A PAYER | G7: COMPTE | H7: INTITULES | I7: OR ADMIS | J7: RECOUVREMENT | K7: RESTE A RECOUVRER
B8: 60 | C8: CHARGES DE PERSONNEL | D8: ='RECAPITULATIF DEPENSES'!F8 -> 0 | E8: ='RECAPITULATIF DEPENSES'!G8 -> 0 | F8: =D8-E8 -> 0 | G8: 70 | H8: IMPOTS SUR LES REVENUS, BENEFICES ET GAINS | I8: ='RECAPITULATIF RECETTES'!G8 -> 0 | J8: ='RECAPITULATIF RECETTES'!H8 -> 0 | K8: ='RECAPITULATIF RECETTES'!I8 -> 0
B9: 61 | C9: ACHATS DE BIENS | D9: ='RECAPITULATIF DEPENSES'!F9 -> 0 | E9: ='RECAPITULATIF DEPENSES'!G9 -> 0 | F9: =D9-E9 -> 0 | G9: 71 | H9: IMPOTS SUR LE PATRIMOINE | I9: ='RECAPITULATIF RECETTES'!G9 -> 0 | J9: ='RECAPITULATIF RECETTES'!H9 -> 0 | K9: ='RECAPITULATIF RECETTES'!I9 -> 0
B10: 62 | C10: ACHATS DE SERVICES ET CHARGES PERMANENTES | D10: ='RECAPITULATIF DEPENSES'!F10 -> 0 | E10: ='RECAPITULATIF DEPENSES'!G10 -> 0 | F10: =D10-E10 -> 0 | G10: 72 | H10: IMPOTS SUR LES BIENS ET SERVICES | I10: ='RECAPITULATIF RECETTES'!G10 -> 0 | J10: ='RECAPITULATIF RECETTES'!H10 -> 0 | K10: ='RECAPITULATIF RECETTES'!I10 -> 0
B11: 63 | C11: DEPENSES D'INTERVENTION | D11: ='RECAPITULATIF DEPENSES'!F11 -> 0 | E11: ='RECAPITULATIF DEPENSES'!G11 -> 0 | F11: =D11-E11 -> 0 | G11: 74 | H11: AUTRES RECETTES FISCALES | I11: ='RECAPITULATIF RECETTES'!G11 -> 0 | J11: ='RECAPITULATIF RECETTES'!H11 -> 0 | K11: ='RECAPITULATIF RECETTES'!I11 -> 0
B12: 64 | C12: IMPOTS ET TAXES | D12: ='RECAPITULATIF DEPENSES'!F12 -> 0 | E12: ='RECAPITULATIF DEPENSES'!G12 -> 0 | F12: =D12-E12 -> 0 | G12: 75 | H12: CONTRIBUTIONS RECUES DES TIERS | I12: ='RECAPITULATIF RECETTES'!G12 -> 0 | J12: ='RECAPITULATIF RECETTES'!H12 -> 0 | K12: ='RECAPITULATIF RECETTES'!I12 -> 0
B13: 65 | C13: TRANSFERTS ET SUBVENTIONS | D13: ='RECAPITULATIF DEPENSES'!F13 -> 0 | E13: ='RECAPITULATIF DEPENSES'!G13 -> 0 | F13: =D13-E13 -> 0 | G13: 76 | H13: PRODUITS FINANCIERS | I13: ='RECAPITULATIF RECETTES'!G13 -> 0 | J13: ='RECAPITULATIF RECETTES'!H13 -> 0 | K13: ='RECAPITULATIF RECETTES'!I13 -> 0
B14: 66 | C14: CHARGES FINANCIERES | D14: ='RECAPITULATIF DEPENSES'!F14 -> 0 | E14: ='RECAPITULATIF DEPENSES'!G14 -> 0 | F14: =D14-E14 -> 0 | G14: 77 | H14: RECETTES NON FISCALES | I14: ='RECAPITULATIF RECETTES'!G14 -> 0 | J14: ='RECAPITULATIF RECETTES'!H14 -> 0 | K14: ='RECAPITULATIF RECETTES'!I14 -> 0
B15: 67 | C15: CHARGES DIVERSES | D15: ='RECAPITULATIF DEPENSES'!F15 -> 0 | E15: ='RECAPITULATIF DEPENSES'!G15 -> 0 | F15: =D15-E15 -> 0
B16: 119 | C16: REPORT A NOUVEAU (DEFICIT) | F16: =D16-E16 -> 0 | G16: 110 | H16: REPORT A NOUVEAU (EXCEDENT) | K16: ='RECAPITULATIF RECETTES'!I16 -> 0
C17: TOTAL DEPENSES REELLES DE FONCTIONNEMENT | D17: =+D8+D9+D10+D11+D12+D13+D14+D15+D16 -> 0 | E17: =+E8+E9+E10+E11+E12+E13+E14+E15+E16 -> 0 | F17: =+F8+F9+F10+F11+F12+F13+F14+F15+F16 -> 0 | H17: TOTAL DEPENSES REELLES DE FONCTIONNEMENT | I17: =+I8+I9+I10+I11+I12+I13++I14+I16 -> 0 | J17: =+J8+J9+J10+J11+J12+J13++J14+J16 -> 0 | K17: =+K8+K9+K10+K11+K12+K13++K14+K16 -> 0
B18: 12 | C18: EXCEDENT DE FONCTIONNEMENT | G18: 774 | H18: PRODUCTION IMMOBILISEE
C19: TOTAL DEPENSES D'ORDRE DE FONCTIONNEMENT | D19: =+D18 -> 0 | E19: =+E18 -> 0 | F19: =+F18 -> 0 | H19: TOTAL DEPENSES D'ORDRE DE FONCTIONNEMENT | I19: =+I18 -> 0 | J19: =+J18 -> 0 | K19: =+K18 -> 0
C20: TOTAL DEPENSES DE FONCTIONNEMENT (2) | D20: =+D17+D19 -> 0 | H20: TOTAL RECETTES DE FONCTIONNEMENT (1) | I20: =+I17+I19 -> 0
C21: EXCEDENT DE FONCTIONNEMENT (1) - (2) | D21: =+I20-D20 -> 0 | H21: DEFICIT DE FONCTIONNEMENT (1) - (2)
C23: SECTION INVESTISSEMENT | H23: SECTION INVESTISSEMENT
B24: COMPTE | C24: INTITULE | D24: MANDAT ADMIS | E24: PAIEMENT | F24: RESTE A PAYER | G24: COMPTE | H24: INTITULE | I24: OR ADMIS | J24: RECOUVREMENT | K24: RESTE A RECOUVRER
B25: 16 | C25: EMPRUNTS ET DETTES ASSIMILEES | D25: ='RECAPITULATIF DEPENSES'!F23 -> 0 | E25: ='RECAPITULATIF DEPENSES'!G23 -> 0 | F25: =+D25-E25 -> 0 | G25: 10 | H25: FONDS, DOTATIONS ET RESERVES | I25: ='RECAPITULATIF RECETTES'!G21 -> 0 | J25: ='RECAPITULATIF RECETTES'!H21 -> 0 | K25: ='RECAPITULATIF RECETTES'!I21 -> 0
B26: 20 | C26: IMMOBILISATION INCORPORELLES | D26: ='RECAPITULATIF DEPENSES'!F24 -> 0 | E26: ='RECAPITULATIF DEPENSES'!G24 -> 0 | F26: =+D26-E26 -> 0 | G26: 13 | H26: SUBVENTIONS D'EQUIPEMENT | I26: ='RECAPITULATIF RECETTES'!G22 -> 0 | J26: ='RECAPITULATIF RECETTES'!H22 -> 0 | K26: ='RECAPITULATIF RECETTES'!I22 -> 0
B27: 21 | C27: IMMOBILISATION CORPORELLES | D27: ='RECAPITULATIF DEPENSES'!F25 -> 0 | E27: ='RECAPITULATIF DEPENSES'!G25 -> 0 | F27: =+D27-E27 -> 0 | G27: 14 | H27: CESSIONS D'IMMOBILISATIONS | I27: ='RECAPITULATIF RECETTES'!G23 -> 0 | J27: ='RECAPITULATIF RECETTES'!H23 -> 0 | K27: ='RECAPITULATIF RECETTES'!I23 -> 0
G28: 16 | H28: EMPRUNTS ET DETTES ASSIMILEES | I28: ='RECAPITULATIF RECETTES'!G24 -> 0 | J28: ='RECAPITULATIF RECETTES'!H24 -> 0 | K28: ='RECAPITULATIF RECETTES'!I24 -> 0
B29: 119 | C29: REPORT A NOUVEAU (DEFICIT) | F29: =+D29-E29 -> 0 | G29: 110 | H29: REPORT A NOUVEAU (EXCEDENT)
C30: TOTAL DEPENSES REELLES D'INVESTISSEMENT | D30: =D25+D26+D27+D29 -> 0 | E30: =E25+E26+E27+E29 -> 0 | F30: =F25+F26+F27+F29 -> 0 | H30: TOTAL DEPENSES REELLES D'INVESTISSEMENT | I30: =+I25+I26+I27+I28+I29 -> 0 | J30: =+J25+J26+J27+J28+J29 -> 0 | K30: =+K25+K26+K27+K28+K29 -> 0
B31: 20 | C31: IMMOBILISATION INCORPORELLES | D31: =+'RECAPITULATIF DEPENSES'!F27 -> 0 | E31: =+'RECAPITULATIF DEPENSES'!G27 -> 0 | F31: =D31-E31 -> 0 | G31: 1012 | H31: DOTATION DE L'ETAT | I31: ='RECAPITULATIF RECETTES'!G26 -> 0 | J31: ='RECAPITULATIF RECETTES'!H26 -> 0 | K31: ='RECAPITULATIF RECETTES'!I26 -> 0
B32: 21 | C32: IMMOBILISATION CORPORELLES | D32: =+'RECAPITULATIF DEPENSES'!F28 -> 0 | E32: =+'RECAPITULATIF DEPENSES'!G28 -> 0 | F32: =D32-E32 -> 0 | G32: 1064 | H32: EXCEDENT DE FONCTIONNEMENT CAPITALISE
C33: TOTAL DEPENSES D'ORDRE D'INVESTISSEMENT | D33: =D31+D32 -> 0 | E33: =E31+E32 -> 0 | F33: =F31+F32 -> 0 | H33: TOTAL DEPENSES D'ORDRE D'INVESTISSEMENT | I33: =I31+I32 -> 0 | J33: =J31+J32 -> 0 | K33: =K31+K32 -> 0
C34: TOTAL DEPENSES D'INVESTISSEMENT (4) | D34: =D30+D33 -> 0 | E34: =E30+E33 -> 0 | F34: =F30+F33 -> 0 | H34: TOTAL RECETTES D'INVESTISSEMENT (3) | I34: =+I30+I33 -> 0 | J34: =+J30+J33 -> 0 | K34: =+K30+K33 -> 0
C35: EXCEDENT D'INVESTISSEMENT (3) - (4) | D35: =I34-D34 -> 0 | H35: DEFICIT D'INVESTISSEMENT (3) - (4)
